{"skeleton":{"hash":"05RctFH3YPRzU3TW9F/bdKgdweQ","spine":"3.6.50","width":0,"height":0,"images":"../images/"},"bones":[{"name":"root","x":-0.75,"y":-1.5},{"name":"bone","parent":"root","x":-1.13,"y":-29.15},{"name":"001_fish_G1_body","parent":"bone","length":74.07,"rotation":90,"x":1.13,"y":3.32,"scaleX":0.989,"scaleY":0.989},{"name":"001_fish_G1_body2","parent":"001_fish_G1_body","x":2.48,"y":-28.17,"color":"ff7f7fff"},{"name":"001_fish_G1_body14","parent":"001_fish_G1_body","x":74.79,"y":6.8,"color":"8bff4dff"},{"name":"001_fish_G1_eye_L","parent":"001_fish_G1_body","x":24.63,"y":-11.71},{"name":"001_fish_G1_teeth_D","parent":"001_fish_G1_body","length":11.66,"rotation":-178.92,"x":-1.35,"y":-29.68},{"name":"001_fish_G1_teeth_U","parent":"001_fish_G1_body","length":5.79,"rotation":1.76,"x":7.55,"y":-28.44},{"name":"001_fish_G2_mouth","parent":"001_fish_G1_body2","x":1.16},{"name":"004_fish_G1_body","parent":"bone","length":38.99,"rotation":179.7,"x":-3.96,"y":12.38,"color":"ff0000ff"},{"name":"004_fish_G1_hand","parent":"004_fish_G1_body","length":32.67,"rotation":25.86,"x":22.83,"y":10.34},{"name":"005_fish_G1_eye","parent":"001_fish_G1_body","x":47.87,"y":-15.05},{"name":"005_fish_G1_eye2","parent":"005_fish_G1_eye","x":0.55,"y":17.59,"color":"ff00e4ff"},{"name":"005_fish_G1_eye3","parent":"005_fish_G1_eye","rotation":-90,"x":-4.37,"y":-15.24,"color":"ff00e4ff"},{"name":"005_fish_G1_head03","parent":"001_fish_G1_body","length":22.39,"x":68.14,"y":-4.29},{"name":"012_fish_G1_hand_L","parent":"004_fish_G1_body","length":30.56,"rotation":159.99,"x":16.54,"y":18.1},{"name":"012_fish_G1_hand_R","parent":"004_fish_G1_body","length":27.59,"rotation":168.23,"x":-18.42,"y":18.97,"transform":"noScale"},{"name":"014_fish_G1_leg","parent":"004_fish_G1_body","length":27.53,"rotation":10.88,"x":44.68,"y":16.56,"color":"ff000091"},{"name":"014_fish_G2_eye_L","parent":"001_fish_G1_body","x":37.35,"y":13.57,"color":"ff000094"},{"name":"014_fish_G2_eye_R","parent":"001_fish_G1_body","x":39.32,"y":-24.24,"color":"ff000094"},{"name":"015_fish_G1_hair03","parent":"001_fish_G1_body14","length":6.03,"rotation":22.78,"x":1.67,"y":-9.23,"color":"8bff4dff"},{"name":"015_fish_G1_hair5","parent":"015_fish_G1_hair03","length":6.05,"rotation":9.45,"x":6.03,"color":"8bff4dff"},{"name":"015_fish_G1_hair6","parent":"015_fish_G1_hair5","length":6.45,"rotation":11.37,"x":6.05,"color":"8bff4dff"},{"name":"016_fish_G3_gun","parent":"012_fish_G1_hand_L","length":37.29,"rotation":14.89,"x":30.57,"y":7.16},{"name":"017_fish_G1_hair03","parent":"001_fish_G1_body","x":78.64,"y":-6.55,"color":"5d6fffff"},{"name":"017_fish_G1_hair01","parent":"017_fish_G1_hair03","length":7.98,"rotation":-136.27,"x":-10.3,"y":-22.66,"color":"5d6fffff"},{"name":"017_fish_G1_hair1","parent":"017_fish_G1_hair01","length":8.15,"rotation":-21.11,"x":7.98,"color":"5d6fffff"},{"name":"017_fish_G1_hair2","parent":"017_fish_G1_hair1","length":9.52,"rotation":-4.18,"x":8.15,"color":"5d6fffff"},{"name":"017_fish_G1_hair02","parent":"017_fish_G1_hair03","length":10.69,"rotation":146.93,"x":-10.18,"y":18.8,"color":"5d6fffff"},{"name":"017_fish_G1_hair3","parent":"017_fish_G1_hair03","length":11.36,"rotation":145.36,"x":-9.51,"y":22.09,"color":"5d6fffff"},{"name":"017_fish_G1_hair4","parent":"017_fish_G1_hair3","length":9.96,"rotation":-2.03,"x":11.36,"color":"5d6fffff"},{"name":"017_fish_G1_hair5","parent":"017_fish_G1_hair4","length":10.16,"rotation":-1.54,"x":9.96,"color":"5d6fffff"},{"name":"017_fish_G1_hair6","parent":"017_fish_G1_hair03","length":10.48,"rotation":-163.03,"x":-17.67,"y":-27.52,"color":"5d6fffff"},{"name":"017_fish_G1_hair7","parent":"017_fish_G1_hair6","length":9.4,"rotation":-4.44,"x":10.48,"color":"5d6fffff"},{"name":"017_fish_G1_hair8","parent":"017_fish_G1_hair7","length":10.26,"rotation":6.81,"x":9.4,"color":"5d6fffff"},{"name":"017_fish_G1_hair9","parent":"017_fish_G1_hair03","length":12.13,"rotation":163.84,"x":-9.66,"y":5.61,"color":"5d6fffff"},{"name":"017_fish_G1_hair10","parent":"017_fish_G1_hair03","length":13.38,"rotation":-175.66,"x":-10.68,"y":-12.8,"color":"5d6fffff"},{"name":"017_fish_G1_hair11","parent":"017_fish_G1_hair2","length":8.56,"rotation":5.15,"x":9.52,"color":"5d6fffff"},{"name":"017_fish_G1_hair12","parent":"017_fish_G1_hair02","length":11.29,"rotation":-4.43,"x":10.69,"color":"5d6fffff"},{"name":"017_fish_G1_hair13","parent":"017_fish_G1_hair12","length":10.86,"rotation":-27.12,"x":10.55,"y":-0.16,"color":"5d6fffff"},{"name":"017_fish_G1_hair14","parent":"017_fish_G1_hair13","length":11.28,"rotation":-19.71,"x":10.86,"color":"5d6fffff"},{"name":"017_fish_G1_hair15","parent":"017_fish_G1_hair11","length":8.52,"rotation":17.38,"x":8.01,"y":-0.02,"color":"5d6fffff"},{"name":"017_fish_G1_hair16","parent":"017_fish_G1_hair03","length":16.57,"rotation":151.66,"x":-13.06,"y":18.35,"color":"5d6fffff"},{"name":"017_fish_G1_hair17","parent":"017_fish_G1_hair16","length":16.17,"rotation":-11.32,"x":16.57,"color":"5d6fffff"},{"name":"017_fish_G1_hair18","parent":"017_fish_G1_hair17","length":13.55,"rotation":-4.85,"x":16.17,"color":"5d6fffff"},{"name":"017_fish_G1_hair19","parent":"017_fish_G1_hair18","length":11.84,"rotation":-3.86,"x":13.55,"color":"5d6fffff"},{"name":"017_fish_G1_hair20","parent":"017_fish_G1_hair19","length":11.93,"rotation":-4.45,"x":11.84,"color":"5d6fffff"},{"name":"017_fish_G2_ear","parent":"001_fish_G1_body","length":10.44,"rotation":69.61,"x":61.15,"y":20.94},{"name":"017_fish_G2_ear2","parent":"017_fish_G2_ear","length":10.38,"rotation":8.54,"x":10.44},{"name":"017_fish_G2_ear3","parent":"017_fish_G2_ear2","length":11.04,"rotation":-0.61,"x":10.38},{"name":"017_fish_G2_ear4","parent":"017_fish_G2_ear3","length":10.56,"rotation":-24.82,"x":11.04},{"name":"017_fish_G2_ear5","parent":"017_fish_G2_ear4","length":8.13,"rotation":-32.89,"x":10.56},{"name":"017_fish_G2_fadai02","parent":"017_fish_G1_hair03","length":21.96,"rotation":49.33,"x":-2.95,"y":16.75,"color":"5d6fffff"},{"name":"017_fish_G2_fadai03","parent":"017_fish_G1_hair03","length":16.36,"rotation":-29.85,"x":-2.82,"y":15.51,"color":"5d6fffff"},{"name":"017_fish_G2_hair03","parent":"017_fish_G1_hair03","length":12.26,"rotation":139.64,"x":-14.11,"y":30.02,"color":"5d6fffff"},{"name":"017_fish_G2_hair3","parent":"017_fish_G2_hair03","length":13.33,"rotation":-5.11,"x":12.26,"color":"5d6fffff"},{"name":"017_fish_G2_hair4","parent":"017_fish_G2_hair3","length":13.89,"rotation":-7.27,"x":13.33,"color":"5d6fffff"},{"name":"017_fish_G2_hair5","parent":"017_fish_G2_hair4","length":13.39,"rotation":-13.97,"x":13.89,"color":"5d6fffff"},{"name":"017_fish_G2_hair6","parent":"017_fish_G2_hair5","length":13.82,"rotation":-0.77,"x":13.39,"color":"5d6fffff"},{"name":"017_fish_G3_bian_stick","parent":"012_fish_G1_hand_R","length":16.01,"rotation":49.9,"x":27.68,"y":-2.73,"color":"ff0000ff"},{"name":"017_fish_G3_bian","parent":"017_fish_G3_bian_stick","length":28.11,"rotation":6.2,"x":13.71,"y":-0.24,"color":"ff0000ff"},{"name":"017_fish_G3_bian01","parent":"017_fish_G3_bian","length":14.4,"rotation":160.7,"x":5.47,"y":-15.75,"color":"ff0000ff"},{"name":"017_fish_G3_bian_eye","parent":"017_fish_G3_bian","rotation":-3.86,"x":16.63,"y":-5.15,"color":"ff0000ff"},{"name":"017_fish_G3_cap01","parent":"005_fish_G1_head03","length":25.86,"rotation":50.01,"x":7.51,"y":30.14},{"name":"017_fish_G3_water","parent":"017_fish_G3_bian","length":11.05,"rotation":118.3,"x":8.69,"y":-3.55,"color":"ff0000ff"}],"slots":[{"name":"017_fish_G3_bian_stick","bone":"017_fish_G3_bian_stick"},{"name":"017_fish_G3_bian","bone":"017_fish_G3_bian"},{"name":"017_fish_G3_bian01","bone":"017_fish_G3_bian01"},{"name":"017_fish_G3_bian_eye","bone":"017_fish_G3_bian_eye"},{"name":"012_fish_G1_hand_R","bone":"012_fish_G1_hand_R"},{"name":"014_fish_G1_leg","bone":"014_fish_G1_leg"},{"name":"001_fish_G1_body","bone":"001_fish_G1_body"},{"name":"001_fish_G1_mouth_back","bone":"001_fish_G2_mouth"},{"name":"001_fish_G1_teeth_D","bone":"001_fish_G1_teeth_D"},{"name":"001_fish_G1_teeth_U","bone":"001_fish_G1_teeth_U"},{"name":"001_fish_G2_mouth","bone":"001_fish_G2_mouth"},{"name":"005_fish_G1_eye","bone":"005_fish_G1_eye"},{"name":"016_fish_G3_gun","bone":"016_fish_G3_gun"},{"name":"014_fish_G2_eye_L","bone":"014_fish_G2_eye_L"},{"name":"014_fish_G2_eye_R","bone":"014_fish_G2_eye_R"},{"name":"017_fish_G1_body","bone":"004_fish_G1_body"},{"name":"017_fish_G1_mouth","bone":"001_fish_G1_eye_L"},{"name":"017_fish_G2_hair03","bone":"017_fish_G2_hair03"},{"name":"017_fish_G1_hair03","bone":"017_fish_G1_hair03"},{"name":"017_fish_G3_cap02","bone":"005_fish_G1_head03"},{"name":"017_fish_G1_hair01","bone":"017_fish_G1_hair01"},{"name":"017_fish_G3_cap01","bone":"017_fish_G3_cap01"},{"name":"017_fish_G2_ear","bone":"017_fish_G2_ear"},{"name":"017_fish_G1_hair02","bone":"017_fish_G1_hair02"},{"name":"017_fish_G2_fadai03","bone":"017_fish_G2_fadai03"},{"name":"017_fish_G2_fadai02","bone":"017_fish_G2_fadai02"},{"name":"017_fish_G2_fadai01","bone":"017_fish_G1_hair03"},{"name":"017_fish_G3_glass","bone":"005_fish_G1_eye"},{"name":"017_fish_G3_glass_L01","bone":"005_fish_G1_eye2"},{"name":"017_fish_G3_glass_R01","bone":"005_fish_G1_eye3"},{"name":"017_fish_G3_hand_L","bone":"004_fish_G1_hand"},{"name":"017_fish_G3_water","bone":"017_fish_G3_water"}],"skins":{"default":{"001_fish_G1_body":{"017_fish_G3_head":{"x":37.94,"y":-5.85,"rotation":-90,"width":82,"height":85}},"001_fish_G1_mouth_back":{"017_fish_G3_mouth_back":{"type":"mesh","uvs":[0.33188,0.09669,0.48812,0.14708,0.72491,0.16487,1,0.11744,0.99999,0.27746,0.94292,0.44872,0.87626,0.66879,0.76885,0.9,0.63214,1,0.33676,1,0.18297,0.81997,0.08777,0.59765,0.03151,0.35128,0,0.10558,0,0,0.18785,0,0.23646,0.4109,0.50265,0.45523,0.73955,0.46995,0.25593,0.64671,0.48058,0.69168,0.73238,0.68868,0.3522,0.84456,0.56945,0.87154,0.1383,0.18894,0.33341,0.28372,0.54316,0.32814,0.76755,0.32518],"triangles":[6,18,5,21,18,6,21,17,18,19,16,17,11,12,16,20,17,21,20,19,17,11,16,19,8,23,7,9,23,8,9,22,23,9,10,22,10,19,22,22,20,23,23,21,7,22,19,20,10,11,19,7,21,6,23,20,21,18,27,5,12,24,16,16,25,17,16,24,25,17,25,26,25,1,26,26,1,2,24,0,25,25,0,1,24,15,0,24,13,15,13,14,15,17,26,18,12,13,24,5,27,4,18,26,27,26,2,27,27,2,4,4,2,3],"vertices":[1,7,6.35,5.6,1,1,7,4.78,0.34,1,1,7,4.03,-7.69,1,1,7,5.07,-17.08,1,2,7,0.59,-16.95,0.69321,6,-9.72,15.86,0.30679,2,7,-4.14,-14.86,0.5,3,1.39,-15.25,0.5,2,3,-4.77,-12.98,0.5,6,1.16,11.45,0.5,1,6,7.56,7.67,1,1,6,10.28,2.97,1,1,6,10.09,-7.07,1,1,6,4.95,-12.2,1,2,3,-2.78,13.83,0.5,6,-1.34,-15.32,0.5,2,7,-0.46,16.03,0.5,3,4.12,15.74,0.5,1,7,6.45,16.89,1,1,7,9.4,16.8,1,1,7,9.21,10.41,1,2,7,-2.34,9.12,0.5,3,2.45,8.77,0.5,2,7,-3.86,0.11,0.5,3,1.21,-0.28,0.5,2,7,-4.52,-7.93,0.5,3,0.8,-8.33,0.5,2,3,-4.15,8.11,0.5,6,0.14,-9.63,0.5,2,3,-5.41,0.47,0.5,6,1.55,-2.02,0.5,2,3,-5.33,-8.09,0.5,6,1.62,6.55,0.5,1,6,5.74,-6.46,1,1,6,6.64,0.91,1,1,7,3.97,12.26,1,1,7,1.11,5.71,1,1,7,-0.35,-1.38,1,1,7,-0.5,-9.01,1],"hull":16,"edges":[26,28,26,24,24,22,22,20,20,18,16,18,16,14,14,12,28,30,30,0,0,2,2,4,8,6,4,6,24,32,32,34,34,36,12,10,36,10,8,10,22,38,38,40,40,42,42,12,20,44,44,46,46,14,26,48,48,50,50,52,52,54,54,8],"width":34,"height":28}},"001_fish_G1_teeth_D":{"017_fish_G3_teeth_d":{"x":3.85,"y":-1.83,"rotation":88.92,"width":23,"height":13}},"001_fish_G1_teeth_U":{"017_fish_G3_teeth_u":{"x":-0.1,"y":-0.26,"rotation":-91.76,"width":29,"height":14}},"001_fish_G2_mouth":{"017_fish_G3_mouth":{"type":"mesh","uvs":[0.38226,0.10756,0.60373,0.14313,0.81002,0.14669,1,0.07555,1,0.27118,0.94048,0.53083,0.8616,0.73357,0.74631,0.9043,0.62193,1,0.38529,1,0.27607,0.9292,0.16079,0.76203,0.07281,0.57351,0,0.34232,0,0.1538,0,0,0.20326,0,0.17967,0.23362,0.35313,0.30989,0.60128,0.32683,0.82052,0.31553,0.19413,0.46241,0.46877,0.5189,0.69524,0.51326,0.27604,0.63471,0.53382,0.67426,0.73138,0.6912,0.34591,0.79571,0.58442,0.82961],"triangles":[10,11,27,9,27,28,10,27,9,8,28,7,9,28,8,11,24,27,27,25,28,28,26,7,11,12,24,27,24,25,28,25,26,7,26,6,12,21,24,24,22,25,25,23,26,6,26,5,12,13,21,24,21,22,25,22,23,26,23,5,14,15,16,17,14,16,17,16,0,2,3,4,18,17,0,18,0,1,20,2,4,19,18,1,19,1,2,19,2,20,13,14,17,21,17,18,13,17,21,23,19,20,22,18,19,22,19,23,21,18,22,5,20,4,23,20,5],"vertices":[1,7,5.71,4.12,1,1,7,4.45,-3.37,1,1,7,4.13,-10.38,1,1,7,5.99,-16.9,1,1,7,0.32,-16.72,1,2,7,-7.14,-14.47,0.49,3,-1.62,-14.95,0.51,2,6,3.88,10.68,0.52,3,-7.5,-12.27,0.48,1,6,8.75,6.67,1,1,6,11.45,2.39,1,1,6,11.3,-5.65,1,1,6,9.17,-9.33,1,1,6,4.25,-13.15,1,2,6,-1.27,-16.04,0.52,3,-2.86,14.55,0.48,2,7,-0.7,17.32,0.49,3,3.84,17.03,0.51,1,7,4.77,17.15,1,1,7,9.23,17.02,1,1,7,9.01,10.11,1,1,7,2.27,11.12,1,1,7,-0.13,5.29,1,1,7,-0.88,-3.13,1,1,7,-0.78,-10.59,1,2,7,-4.38,10.83,0.49,3,0.36,10.43,0.51,2,7,-6.31,1.55,0.49,3,-1.28,1.09,0.51,2,7,-6.38,-6.15,0.49,3,-1.11,-6.61,0.51,2,6,0.64,-9.17,0.52,3,-4.64,7.64,0.48,2,6,1.95,-0.43,0.52,3,-5.78,-1.12,0.48,2,6,2.57,6.28,0.52,3,-6.27,-7.84,0.48,1,6,5.35,-6.88,1,1,6,6.49,1.21,1],"hull":17,"edges":[28,30,26,28,26,24,24,22,22,20,20,18,16,18,16,14,14,12,12,10,10,8,30,32,32,0,0,2,2,4,8,6,4,6,28,34,34,36,36,38,38,40,26,42,42,44,44,46,46,10,24,48,48,50,50,52,52,12,22,54,54,56,56,14],"width":34,"height":29}},"005_fish_G1_eye":{"017_fish_G2_eye":{"x":-3.89,"y":4.72,"rotation":-90,"width":52,"height":26}},"012_fish_G1_hand_R":{"017_fish_G3_hand_R":{"x":15.66,"y":-2.19,"rotation":12.07,"width":35,"height":16}},"014_fish_G1_leg":{"017_fish_G1_leg":{"x":4.95,"y":-0.81,"rotation":169.42,"width":20,"height":12},"017_fish_G3_leg":{"x":6.96,"y":3.97,"rotation":169.42,"width":21,"height":24}},"014_fish_G2_eye_L":{"017_fish_G2_eye_L":{"x":0.25,"y":-0.53,"rotation":-90,"width":15,"height":15}},"014_fish_G2_eye_R":{"017_fish_G2_eye_R":{"x":0.02,"y":-0.19,"rotation":-90,"width":13,"height":14}},"016_fish_G3_gun":{"016_fish_G3_gun":{"x":9.79,"y":-0.84,"rotation":32.44,"width":62,"height":48}},"017_fish_G1_body":{"017_fish_G1_body":{"x":12.42,"y":-6.44,"rotation":-179.7,"width":84,"height":64},"017_fish_G3_body":{"x":18.14,"y":-4.75,"rotation":-179.7,"width":85,"height":69}},"017_fish_G1_hair01":{"017_fish_G1_hair01":{"type":"mesh","uvs":[0.34826,0.12452,0.5046,0.28749,0.61243,0.46817,0.70947,0.65949,0.83886,0.7764,1,0.87206,1,1,0.78495,1,0.57469,0.94292,0.42912,0.82246,0.32669,0.64177,0.26739,0.47172,0.14878,0.30166,0,0.16703,0,0,0.16495,0],"triangles":[7,5,6,7,4,5,7,8,4,8,3,4,8,9,3,9,10,3,10,2,3,10,11,2,11,1,2,1,11,12,1,12,0,12,15,0,12,13,15,13,14,15],"vertices":[1,25,4.42,3.73,1,2,25,11.1,2.37,0.02377,26,2.06,3.34,0.97623,2,26,8.93,3.19,0.40036,27,0.54,3.24,0.59964,2,27,7.5,3.16,0.80465,37,-0.77,3.64,0.19535,2,27,11.29,5.61,0.12,37,3.47,4.48,0.88,1,37,8.06,6.58,1,1,37,12.21,4.76,1,1,37,10.21,0.18,1,2,27,17.01,-1.11,0.00149,37,6.4,-3.5,0.99851,2,27,11.88,-4.56,0.39232,37,0.61,-4.98,0.60768,3,26,12.04,-5.31,0.03467,27,4.27,-5.01,0.9649,37,-6.68,-2.84,4.3E-4,3,25,12,-6.12,0.00274,26,5.95,-4.26,0.8408,27,-1.88,-4.41,0.15646,2,25,5.74,-3.96,0.67724,26,-0.66,-4.5,0.32276,1,25,-0.09,-3.16,1,1,25,-4.36,0.92,1,1,25,-1.71,3.7,1],"hull":16,"edges":[26,28,26,24,24,22,22,20,20,18,18,16,12,14,16,14,12,10,10,8,8,6,6,4,4,2,2,0,28,30,0,30],"width":23,"height":35},"017_fish_G2_hair02":{"type":"mesh","uvs":[0.34096,0.13979,0.46953,0.26816,0.5681,0.41607,0.65382,0.56397,0.73096,0.71188,0.86382,0.82351,1,0.89886,1,1,0.74382,1,0.58096,0.92397,0.49096,0.81234,0.40096,0.66444,0.33668,0.50816,0.24239,0.36025,0.13953,0.24583,0,0.10909,0,0,0.16096,0],"triangles":[8,5,7,5,6,7,5,8,4,8,9,4,9,10,4,10,3,4,10,11,3,11,2,3,11,12,2,12,1,2,12,13,1,13,0,1,13,14,0,14,17,0,14,15,17,15,16,17],"vertices":[2,25,5.3,3.45,0.99252,26,-3.74,2.26,0.00748,2,25,11.78,2.24,0.00925,26,2.74,3.46,0.99075,2,26,9.67,3.56,0.17517,27,1.25,3.66,0.82483,2,27,8.05,3.93,0.74996,37,-1.11,4.04,0.25004,2,37,5.58,3.48,0.98479,41,-1.27,4.06,0.01521,2,37,11.47,4.97,0.02059,41,4.79,3.72,0.97941,1,41,9.74,4.48,1,1,41,13.02,1.63,1,2,37,17.08,-1.15,0.04015,41,8.32,-3.79,0.95985,2,37,12.26,-4.02,0.31411,41,2.86,-5.09,0.68589,2,37,6.85,-4.41,0.34273,41,-2.41,-3.85,0.65727,3,27,9.91,-4.16,0.43785,37,0.01,-4.17,0.53751,41,-8.87,-1.58,0.02465,2,26,10.83,-3.95,0.05817,27,2.96,-3.74,0.94183,3,25,10.25,-5.09,0.07894,26,3.95,-3.94,0.87578,27,-3.91,-4.23,0.04528,2,25,4.7,-3.77,0.88783,26,-1.7,-4.7,0.11217,1,25,-2.25,-2.53,1,1,25,-5.64,0.71,1,1,25,-2.53,3.97,1],"hull":18,"edges":[30,32,30,28,28,26,26,24,24,22,22,20,20,18,14,16,18,16,14,12,12,10,10,8,8,6,6,4,4,2,2,0,32,34,0,34],"width":28,"height":43},"017_fish_G3_hair02":{"type":"mesh","uvs":[0.23262,0.05627,0.34966,0.14825,0.43844,0.23497,0.51916,0.34534,0.58777,0.44783,0.6483,0.55294,0.68866,0.65806,0.75727,0.75004,0.86623,0.82362,1,0.88143,1,1,0.82991,1,0.67252,1,0.56355,0.90771,0.4788,0.81311,0.4223,0.71325,0.37387,0.59499,0.31737,0.46885,0.23666,0.35059,0.11962,0.23234,0,0.10883,0,0,0.14384,0],"triangles":[12,13,7,12,7,8,11,12,8,11,8,9,11,9,10,15,5,6,14,15,6,13,14,6,13,6,7,4,16,17,4,17,3,16,4,5,15,16,5,18,1,2,17,18,2,17,2,3,20,21,22,19,20,22,19,22,0,19,0,1,18,19,1],"vertices":[1,25,0.35,4.01,1,2,25,5.53,3.64,0.97489,26,-3.6,2.51,0.02511,2,25,9.99,2.85,0.15069,26,0.85,3.38,0.84931,2,26,6.16,3.65,0.86052,27,-2.25,3.49,0.13948,2,26,11.02,3.72,0.03329,27,2.59,3.92,0.96671,2,27,7.47,4.1,0.85998,37,-1.67,4.27,0.14002,3,27,12.17,3.74,0.05497,37,2.97,3.49,0.92592,41,-3.75,4.85,0.01911,2,37,7.42,3.67,0.2554,41,0.54,3.7,0.7446,1,41,4.98,3.93,1,1,41,9.36,5.14,1,1,41,13.25,1.76,1,2,37,18.2,1.21,0.01515,41,10.1,-1.87,0.98485,2,37,16.42,-2.88,0.21476,41,7.18,-5.24,0.78524,2,37,11.51,-4.1,0.70614,41,2.12,-4.94,0.29386,2,37,6.78,-4.65,0.53654,41,-2.56,-4.06,0.46346,3,27,12.06,-4.17,0.08371,37,2.16,-4.38,0.82487,41,-6.89,-2.42,0.09142,3,27,6.75,-3.85,0.94715,37,-3.1,-3.58,0.05236,41,-11.67,-0.08,4.9E-4,2,26,8.92,-3.69,0.29114,27,1.04,-3.63,0.70886,3,25,9.68,-4.76,0.08388,26,3.29,-3.83,0.91315,27,-4.56,-4.17,0.00297,2,25,3.67,-3.6,0.95212,26,-2.73,-4.91,0.04788,1,25,-2.55,-2.33,1,1,25,-5.97,0.94,1,1,25,-3.16,3.88,1],"hull":23,"edges":[40,42,40,38,38,36,36,34,34,32,32,30,30,28,28,26,26,24,20,22,22,24,20,18,18,16,16,14,14,12,12,10,10,8,8,6,6,4,4,2,2,0,42,44,0,44],"width":28,"height":43}},"017_fish_G1_hair02":{"017_fish_G1_hair02":{"type":"mesh","uvs":[1,0.2912,0.87395,0.5058,0.75184,0.6856,0.56105,0.848,0.36263,1,0.19474,1,0,0.8944,0,0.7494,0.12605,0.6392,0.32447,0.4594,0.5,0.2274,0.65263,0,1,0],"triangles":[3,9,2,8,9,3,5,6,7,4,5,8,5,7,8,3,4,8,11,12,0,10,11,0,1,10,0,2,10,1,9,10,2],"vertices":[1,28,1.02,3.82,1,2,28,6.89,4.76,0.92876,38,-4.15,4.45,0.07124,2,28,11.98,5.27,0.25483,38,0.88,5.35,0.74517,2,28,17.42,4.44,1.0E-4,38,6.37,4.95,0.9999,1,38,11.74,4.26,1,1,38,13.7,1.7,1,1,38,13.86,-2.89,1,1,38,10.95,-5.12,1,2,28,17.56,-5.45,0,38,7.27,-4.9,1,2,28,11.67,-4.73,0.29331,38,1.34,-4.64,0.70669,2,28,4.91,-5.11,0.98875,38,-5.36,-5.54,0.01125,1,28,-1.5,-5.79,1,1,28,-5.15,-0.19,1],"hull":13,"edges":[22,24,22,20,20,18,18,16,16,14,12,14,12,10,8,10,8,6,6,4,4,2,0,24,2,0],"width":19,"height":25},"017_fish_G2_hair01":{"type":"mesh","uvs":[1,0.08976,0.91251,0.24438,0.84168,0.40571,0.77085,0.57712,0.68231,0.72165,0.55246,0.84601,0.41375,0.92668,0.25734,1,0.10683,1,0,1,0,0.80904,0.09502,0.77879,0.22487,0.76198,0.37834,0.6914,0.48163,0.60065,0.58787,0.45276,0.66756,0.29815,0.76199,0.12338,0.90955,0,1,0],"triangles":[8,9,10,8,11,12,7,8,12,8,10,11,6,7,12,13,14,5,6,13,5,12,13,6,4,15,3,14,15,4,5,14,4,18,19,0,0,17,18,1,17,0,16,17,1,2,16,1,15,16,2,3,15,2],"vertices":[1,28,-8.56,3,1,1,28,-1.94,3.03,1,1,28,4.52,3.77,1,2,28,11.27,4.7,0.43359,38,0.22,4.73,0.56641,1,38,6.56,5.02,1,2,38,13.35,3.52,0.91344,39,0.81,4.55,0.08656,3,38,19.11,0.78,0.09642,39,7.2,4.74,0.88683,40,-5.04,3.23,0.01675,2,39,14.12,4.38,0.12382,40,1.6,5.22,0.87618,1,40,7.74,4.61,1,1,40,12.1,4.18,1,1,40,11.42,-2.66,1,1,40,7.44,-3.36,1,2,39,11.65,-3.93,0.19847,40,2.08,-3.43,0.80153,2,39,4.88,-3.53,0.99905,40,-4.43,-5.34,9.5E-4,2,38,8.11,-4.16,0.44227,39,-0.35,-4.67,0.55773,3,28,11.61,-4.03,0.32961,38,1.23,-3.95,0.66625,39,-6.56,-7.62,0.00414,2,28,5.17,-4.33,0.99999,38,-5.17,-4.74,1.0E-5,1,28,-2.22,-4.52,1,1,28,-9.24,-1.87,1,1,28,-11.26,1.24,1],"hull":20,"edges":[36,38,36,34,34,32,32,30,30,28,28,26,26,24,24,22,18,20,22,20,16,18,14,16,14,12,12,10,10,8,8,6,6,4,4,2,0,38,2,0],"width":41,"height":36},"017_fish_G3_hair01":{"type":"mesh","uvs":[1,0.10109,0.92455,0.21825,0.85957,0.34159,0.81626,0.46492,0.76031,0.60469,0.68992,0.71775,0.58524,0.81641,0.4625,0.90275,0.33255,0.9603,0.20441,1,0.09612,1,0,1,0,0.81436,0.11417,0.78558,0.2387,0.7568,0.37046,0.69103,0.47875,0.60469,0.56177,0.50808,0.63036,0.38064,0.69714,0.22853,0.79821,0.09698,0.89567,0,1,0],"triangles":[3,17,18,3,18,2,18,19,2,2,19,1,19,20,1,1,20,0,0,20,21,21,22,0,6,16,5,16,17,5,5,17,4,4,17,3,8,14,7,14,15,7,7,15,6,15,16,6,10,13,9,8,9,14,9,13,14,13,10,12,10,11,12],"vertices":[1,28,-8.75,3.42,1,1,28,-3.47,3.13,1,1,28,1.77,3.32,1,2,38,-4.5,3.93,0.02616,28,6.51,4.26,0.97384,2,38,0.95,5.19,0.7376,28,12.04,5.1,0.2624,2,38,5.99,5.38,0.99953,28,17.08,4.9,4.7E-4,2,39,-1.11,4.24,0.00438,38,11.49,4.12,0.99562,2,39,4.83,4.9,0.72053,38,17.08,2,0.27947,3,40,-1.76,4.13,0.3238,39,10.6,4.48,0.66936,38,22.02,-1,0.00684,2,40,3.67,5.04,0.99235,39,16.02,3.51,0.00765,1,40,8.14,4.6,1,1,40,12.11,4.21,1,1,40,11.44,-2.52,1,1,40,6.63,-3.09,1,2,40,1.39,-3.63,0.64726,39,10.94,-3.88,0.35274,2,40,-4.29,-5.47,9.1E-4,39,4.98,-3.7,0.99909,2,39,-0.43,-4.62,0.6202,38,8.06,-4.08,0.3798,3,39,-5.05,-6.32,0.02919,38,3.17,-3.49,0.92964,28,13.58,-3.72,0.04118,2,38,-2.24,-4.06,0.1037,28,8.14,-3.87,0.8963,1,28,1.99,-4.57,1,1,28,-4.31,-3.67,1,1,28,-9.47,-2.21,1,1,28,-11.83,1.41,1],"hull":23,"edges":[42,44,42,40,40,38,38,36,36,34,34,32,32,30,30,28,28,26,22,24,26,24,20,22,18,20,18,16,16,14,14,12,12,10,10,8,8,6,6,4,4,2,0,44,2,0],"width":41,"height":36}},"017_fish_G1_hair03":{"017_fish_G1_hair03":{"type":"mesh","uvs":[0.79332,0.08127,0.85471,0.18779,0.90246,0.32002,0.93885,0.49265,0.95931,0.66529,1,0.82323,1,1,0.90474,1,0.882,0.87833,0.8729,0.7461,0.85926,0.6359,0.84107,0.52938,0.81379,0.60285,0.66218,0.57443,0.50362,0.54471,0.40223,0.52571,0.35448,0.64692,0.33174,0.7461,0.30673,0.85262,0.23851,0.91873,0.17257,0.9224,0.09754,0.83425,0,0.76079,0,0.62488,0.05888,0.51102,0.11345,0.37512,0.16575,0.24288,0.23851,0.10698,0.37949,0,0.53183,0,0.691,0,0.27971,0.35379,0.47938,0.29438,0.69813,0.33678,0.83113,0.38767,0.22563,0.48096,0.18363,0.60817,0.13463,0.73255],"triangles":[20,21,19,18,19,37,19,21,37,18,37,17,21,22,37,22,23,37,37,36,17,37,23,36,23,24,36,17,36,16,36,35,16,16,35,15,36,24,35,24,25,35,35,25,31,35,31,15,25,26,31,32,31,27,31,26,27,6,8,5,6,7,8,8,9,5,9,4,5,9,10,4,10,3,4,10,11,3,11,34,3,34,2,3,2,34,1,12,13,11,13,34,11,13,33,34,13,14,33,34,33,1,33,0,1,33,30,0,32,29,30,32,28,29,27,28,32,15,32,14,14,32,33,15,31,32,33,32,30],"vertices":[3,24,-0.29,-20,0.15055,36,-9.81,7.97,0.726,32,-18.82,-2.12,0.12345,3,24,-5.89,-25.22,0.02381,36,-3.83,12.75,0.57717,32,-11.94,1.23,0.39902,2,36,3.41,16.27,0.13198,32,-4.11,3.08,0.86802,1,32,5.48,3.39,1,1,33,3.99,2.72,1,2,33,12.85,4.29,0.01069,34,3.93,3.86,0.98931,1,34,12.71,0.78,1,1,34,10.03,-6.86,1,2,33,13.5,-6.12,0.07779,34,3.35,-6.56,0.92221,2,33,6.55,-5.37,0.888,34,-3.47,-4.99,0.112,3,36,19.69,11.35,0.00875,32,10.71,-5.27,0.31815,33,0.64,-5.24,0.6731,3,36,13.99,10.23,0.26232,32,4.9,-5.12,0.70916,33,-5.17,-5.53,0.02852,2,36,17.67,7.63,0.63265,32,7.92,-8.46,0.36735,2,35,11.87,18.51,0.13009,36,15.2,-5.1,0.86991,2,35,14.12,5.14,0.86822,36,12.62,-18.41,0.13178,4,35,15.56,-3.41,0.69661,29,6.6,15.33,0.15888,30,-5.3,15.16,0.12816,31,-15.66,14.74,0.01635,4,35,22.81,-5.53,0.22359,29,14.15,15.62,0.13089,30,2.23,15.71,0.46017,31,-8.14,15.5,0.18534,4,35,28.36,-5.94,0.09431,29,19.53,17,0.03393,30,7.57,17.27,0.44056,31,-2.85,17.2,0.4312,4,35,34.33,-6.42,0.04199,29,25.35,18.43,0.00287,30,13.33,18.92,0.31452,31,2.87,19,0.64063,3,35,39.28,-11.02,0.01667,30,19.58,16.35,0.18023,31,9.18,16.6,0.8031,3,35,41.03,-16.34,0.00646,30,23.08,11.97,0.09423,31,12.8,12.32,0.89931,3,35,38.35,-23.75,3.1E-4,30,23.17,4.09,0.00804,31,13.1,4.44,0.99166,1,31,15.19,-4.46,1,2,30,19.29,-9.13,0.0102,31,9.57,-8.88,0.9898,3,29,22.54,-9.1,0.0027,30,11.5,-8.7,0.34658,31,1.77,-8.65,0.65072,3,29,14.02,-9.35,0.27712,30,3,-9.25,0.67875,31,-6.71,-9.43,0.04413,2,29,5.78,-9.65,0.86772,30,-5.23,-9.84,0.13228,3,35,-1.72,-22.9,0.00363,24,-1.64,27.13,0.49,29,-3.62,-8.62,0.50637,1,24,3.99,15.15,1,1,24,3.99,2.21,1,1,24,3.99,-11.31,1,3,35,9.77,-15.92,0.0364,29,5.07,1.63,0.96095,30,-6.34,1.41,0.00265,2,35,2.05,-0.5,0.98991,29,-7.14,13.81,0.01009,3,35,-0.98,17.96,0.01996,24,-13.72,-11.92,0.00276,36,2.97,-1.11,0.97728,2,36,6.49,9.95,0.3342,32,-2.47,-3.75,0.6658,4,35,17.48,-18.48,0.015,29,13.19,1.65,0.07776,30,1.77,1.72,0.90574,31,-8.23,1.5,0.0015,3,35,24.89,-20.04,0.00898,30,9.27,2.85,0.64064,31,-0.77,2.83,0.35038,3,35,32.33,-22.22,0.00188,30,17,3.42,0.02093,31,6.95,3.61,0.97719],"hull":31,"edges":[46,48,48,50,50,52,52,54,54,56,56,58,58,60,60,0,0,2,2,4,4,6,6,8,12,10,8,10,12,14,14,16,16,18,18,20,20,22,22,24,30,32,32,34,34,36,36,38,38,40,40,42,44,46,42,44,28,30,24,26,26,28,52,62,62,30,22,6,62,64,64,66,66,68,68,22,62,70,70,72,72,74,74,42],"width":84,"height":52},"017_fish_G2_hair04":{"type":"mesh","uvs":[0.80319,0.03776,0.88939,0.13712,0.93398,0.25808,0.95776,0.3704,0.96965,0.47624,0.97708,0.5864,1,0.67928,1,0.80024,0.92952,0.79376,0.91912,0.72464,0.90128,0.61232,0.88196,0.49784,0.86561,0.4028,0.85075,0.4784,0.78238,0.44816,0.67538,0.43304,0.57877,0.42656,0.49703,0.39416,0.48514,0.45032,0.46284,0.53024,0.43015,0.63824,0.38259,0.73328,0.32462,0.83048,0.26963,0.91904,0.21018,1,0.07196,1,0,1,0,0.92552,0.03778,0.87368,0.09723,0.80888,0.17451,0.69224,0.25477,0.58856,0.32611,0.48488,0.36772,0.392,0.26666,0.30128,0.34097,0.15224,0.42272,0.03344,0.5758,0,0.70213,0,0.41976,0.24449,0.54679,0.2037,0.69154,0.21229,0.80675,0.23375,0.85401,0.3003],"triangles":[43,42,2,40,39,36,39,35,36,34,35,39,40,36,37,41,37,38,41,38,0,1,42,0,42,1,2,40,37,41,42,41,0,10,5,6,9,10,6,7,8,9,7,9,6,11,4,5,10,11,5,43,2,3,12,43,3,12,3,4,4,11,12,15,41,42,15,42,43,14,15,43,12,14,43,13,14,12,16,40,41,17,40,16,15,16,41,25,26,27,24,25,28,29,24,28,25,27,28,23,29,22,23,24,29,30,31,21,22,30,21,29,30,22,20,32,19,31,32,20,21,31,20,33,34,39,17,39,40,33,39,17,18,33,17,32,33,18,19,32,18],"vertices":[1,24,6.65,-17.87,1,1,24,-0.8,-27.27,1,3,36,0.67,19.33,0.04595,32,-6.11,6.68,0.24405,24,-9.88,-32.13,0.71,2,32,2.7,6.7,0.99992,33,-8.27,6.08,8.0E-5,2,32,10.67,5.62,0.53515,33,-0.24,5.62,0.46485,2,33,8,4.62,0.70151,34,-0.84,4.75,0.29849,2,33,15.34,5.54,0.00433,34,6.56,4.8,0.99567,1,34,15.12,1.8,1,1,34,12.12,-5.29,1,1,34,6.85,-4.64,1,2,33,8.1,-3.87,0.76312,34,-1.74,-3.69,0.23688,3,36,18.17,12.32,3.0E-5,32,9.43,-3.99,0.6587,33,-0.73,-4.06,0.34127,2,36,10.92,11.08,0.22353,32,2.1,-3.62,0.77647,2,36,16.46,9.04,0.58565,32,7.05,-6.82,0.41435,2,36,13.63,1.78,0.91474,32,2.7,-13.29,0.08526,3,42,-1.84,24.33,0.00201,35,10.15,12.88,0.41692,36,11.62,-9.77,0.58107,3,42,2.73,14.83,0.00957,35,12.61,2.63,0.94569,36,10.33,-20.23,0.04474,3,42,4.83,5.84,0.71036,35,12.76,-6.6,0.28954,36,7.24,-28.93,1.0E-4,4,42,9.15,6.7,0.95576,43,-8.59,5.11,0.00458,35,17.17,-6.67,0.03963,36,11.34,-30.54,3.0E-5,3,42,15.58,7.4,0.61508,43,-2.42,7.06,0.38491,36,17.13,-33.42,1.0E-5,4,42,24.4,8.11,0.01511,43,6.09,9.49,0.9743,44,-10.85,8.6,0.01059,36,24.94,-37.59,0,2,43,14.88,10.05,0.62271,44,-2.13,9.9,0.37729,3,43,24.53,9.84,0.04444,44,7.49,10.51,0.85332,45,-6.75,10.08,0.10224,3,44,16.43,10.89,0.31094,45,2.14,11.06,0.67081,46,-10.53,10.27,0.01825,3,44,25.31,10.53,0.01027,45,11.02,11.29,0.7255,46,-1.69,11.19,0.26424,1,46,10.31,2.09,1,1,46,16.56,-2.65,1,1,46,13.18,-7.1,1,2,45,18.77,-8.27,0.0176,46,7.55,-7.71,0.9824,3,44,23.71,-8.3,0.00635,45,10.7,-7.6,0.58331,46,-0.55,-7.67,0.41034,3,43,26.99,-9.38,1.2E-4,44,11.57,-8.43,0.64408,45,-1.41,-8.54,0.3558,2,43,15.42,-7.6,0.51268,44,-0.11,-7.64,0.48732,2,42,19.66,-7.33,0.1253,43,4.47,-6.58,0.8747,2,42,11.37,-6.64,0.93232,43,-3.79,-7.53,0.06768,1,24,-13.12,40.61,1,1,24,-1.94,32.51,1,1,24,6.97,23.6,1,1,24,9.48,6.92,1,1,24,9.48,-6.85,1,3,42,-1.06,-6.9,0.65346,35,4.32,-17.81,0.01654,24,-8.86,23.92,0.33,4,42,-10.32,3.83,0.18601,35,-2.47,-5.37,0.47828,36,-6.6,-22.44,0.00571,24,-5.8,10.08,0.33,4,35,-6.24,9.97,0.25955,36,-4.76,-6.76,0.41044,32,-17.11,-17.6,1.0E-5,24,-6.44,-5.7,0.33,4,35,-8.19,22.48,0.00417,36,-2.2,5.64,0.52736,32,-11.9,-6.06,0.13847,24,-8.05,-18.26,0.33,2,36,3.16,10.4,0.39174,32,-5.63,-2.58,0.60826],"hull":39,"edges":[74,72,72,70,70,68,68,66,66,64,64,62,62,60,60,58,58,56,52,54,56,54,50,52,48,50,48,46,46,44,44,42,42,40,40,38,38,36,36,34,34,32,32,30,30,28,28,26,26,24,24,22,22,20,20,18,18,16,16,14,14,12,12,10,10,8,8,6,6,4,4,2,2,0,74,76,0,76,24,6,66,34,66,78,78,80,80,82,82,84,84,86,86,24],"width":109,"height":75},"017_fish_G3_hair04":{"type":"mesh","uvs":[0.85882,0.08732,0.9317,0.22477,0.97356,0.33744,1,0.47489,1,0.5808,1,0.6822,1,0.78135,0.92704,0.77008,0.91619,0.70023,0.90379,0.61009,0.88673,0.50644,0.86968,0.40955,0.84642,0.47264,0.74409,0.45236,0.6092,0.42532,0.51152,0.40504,0.48672,0.48841,0.43555,0.63263,0.38128,0.73628,0.33322,0.83092,0.26965,0.92781,0.21073,1,0.15027,1,0.05879,1,0,1,0,0.91204,0.04173,0.86923,0.1084,0.77909,0.19368,0.67544,0.265,0.58305,0.33632,0.4794,0.36423,0.39377,0.2712,0.29012,0.33167,0.17295,0.42935,0.04451,0.55183,0,0.72549,0,0.1084,0.95035,0.4371,0.37124,0.51462,0.24055,0.65882,0.21351,0.7906,0.25181,0.85572,0.3104],"triangles":[32,33,38,1,41,0,40,36,0,40,35,36,39,35,40,41,40,0,39,34,35,33,34,39,42,1,2,8,9,5,7,8,5,7,5,6,10,3,4,9,10,4,9,4,5,11,42,2,13,42,11,11,2,3,3,10,11,14,40,41,13,14,41,13,41,42,12,13,11,42,41,1,14,39,40,15,39,14,37,26,27,25,26,37,23,24,25,37,23,25,21,22,37,23,37,22,20,27,19,20,37,27,20,21,37,28,29,18,19,28,18,27,28,19,17,30,16,29,30,17,18,29,17,38,33,39,31,32,38,15,38,39,16,38,15,31,16,30,16,31,38],"vertices":[1,24,3.31,-24.63,1,1,24,-7.11,-32.67,1,4,36,6.82,24.04,8.5E-4,32,0.92,9.92,0.64232,33,-10.3,9.15,0.01682,24,-15.66,-37.28,0.34,3,32,11.75,9.67,0.46246,33,0.51,9.74,0.52157,34,-7.67,10.72,0.01597,3,32,19.43,7.32,0.03863,33,8.36,7.99,0.59641,34,-0.09,8.06,0.36496,2,33,15.86,6.32,0.04035,34,7.17,5.51,0.95965,1,34,14.26,3.02,1,1,34,10.8,-4.28,1,1,34,5.4,-3.66,1,2,33,8.22,-2.84,0.84963,34,-1.5,-2.68,0.15037,4,42,-8.3,47.86,0,35,8.79,37.24,0,32,10.39,-2.97,0.49259,33,0.14,-2.97,0.50741,4,42,-13.88,42.71,0,35,2.26,33.39,3.0E-4,36,11.41,12.2,0.12211,32,2.81,-2.63,0.8776,4,42,-8.45,42.73,0,35,7.57,32.26,0.00151,36,15.99,9.29,0.50407,32,6.64,-6.48,0.49442,3,42,-4.45,32.07,5.0E-5,35,9.23,21,0.01889,36,13.6,-1.85,0.98106,4,42,0.81,18.01,0.00171,35,11.4,6.15,0.81658,36,10.43,-16.52,0.18163,32,-4.42,-30.44,8.0E-5,4,42,4.56,7.8,0.55406,35,12.92,-4.62,0.44476,36,8.08,-27.14,0.00118,32,-9.03,-40.29,0,5,42,11.43,8.4,0.85949,43,-6.69,7.23,0.09542,35,19.75,-5.49,0.04465,36,14.18,-30.34,4.4E-4,32,-3.78,-44.75,0,5,42,23.73,8.63,0.05667,43,5.33,9.87,0.93576,44,-11.63,8.91,0.00755,36,24.65,-36.79,2.0E-5,32,5.03,-53.34,0,2,43,15.2,10.28,0.59151,44,-1.83,10.16,0.40849,3,43,24.11,10.78,0.06118,44,7,11.41,0.83057,45,-7.31,10.95,0.10825,3,44,17.15,11.57,0.28596,45,2.81,11.78,0.69923,46,-9.91,11.05,0.01481,3,44,25.61,10.77,0.01735,45,11.3,11.56,0.75897,46,-1.43,11.48,0.22368,2,45,16.28,7.13,0.34005,46,3.88,7.46,0.65995,2,46,11.91,1.36,1,32,19.56,-101.19,0,1,46,17.08,-2.56,1,1,46,13.05,-7.87,1,3,45,18.64,-8.23,0.04698,46,7.42,-7.68,0.95302,32,9.53,-100.09,0,4,44,21.57,-9.02,0.01428,45,8.6,-8.46,0.79208,46,-2.57,-8.68,0.19364,32,5.13,-91.07,0,2,44,9.37,-7.82,0.8314,45,-3.65,-8.09,0.1686,2,43,14.44,-7.01,0.64524,44,-1.14,-7.13,0.35476,2,42,18.7,-6.52,0.17843,43,3.37,-5.97,0.82157,2,42,11.52,-6.89,0.95899,43,-3.6,-7.75,0.04101,1,24,-12.07,40.14,1,1,24,-3.18,33.47,1,1,24,6.56,22.71,1,1,24,9.94,9.2,1,1,24,9.94,-9.94,1,2,45,17.23,1.25,0.02623,46,5.28,1.67,0.97377,1,42,6.2,-0.63,1,4,42,-6.58,2.18,0.4986,35,0.84,-7.77,0.4299,36,-4.34,-25.85,0,24,-8.31,13.31,0.07149,3,35,-5.55,6.93,0.29875,36,-5.18,-9.85,0.26844,24,-6.26,-2.59,0.43281,3,36,-1.18,4.42,0.79857,32,-11.17,-7.47,0.16528,24,-9.16,-17.11,0.03615,5,42,-19.76,37.79,0,35,-4.54,29.82,3.0E-5,36,3.79,11.24,0.30329,32,-4.83,-1.9,0.69232,24,-13.61,-24.29,0.00435],"hull":37,"edges":[70,68,68,66,66,64,64,62,62,60,60,58,58,56,56,54,54,52,48,50,52,50,46,48,46,74,44,46,74,44,42,44,42,40,40,38,38,36,36,34,34,32,32,30,30,28,28,26,26,24,24,22,22,20,20,18,18,16,16,14,14,12,12,10,10,8,8,6,6,4,4,2,2,0,70,72,0,72,62,76,76,30,76,78,78,80,80,82,82,84,84,22,80,28,82,26,78,30],"width":109,"height":75}},"017_fish_G1_mouth":{"017_fish_G1_mouth":{"x":-1.51,"y":-0.27,"rotation":-90,"width":9,"height":11},"017_fish_G2_mouth":{"x":-2.1,"y":-0.24,"rotation":-90,"width":26,"height":21}},"017_fish_G2_ear":{"017_fish_G2_ear":{"x":3.64,"y":0.29,"rotation":-159.61,"width":14,"height":13},"017_fish_G3_ear":{"type":"mesh","uvs":[0.185,0.09733,0.26943,0.22629,0.39343,0.32549,0.54381,0.32549,0.69947,0.37013,0.86568,0.53877,1,0.70741,0.99472,0.89589,0.92636,1,0.75751,1,0.60977,1,0.43036,1,0.28526,1,0.13224,0.81157,0.0399,0.59829,0,0.40485,0,0,0.1296,0,0.81555,0.79173,0.65198,0.68261,0.48313,0.66773,0.29317,0.61813,0.15071,0.43957,0.07947,0.25605],"triangles":[0,23,16,0,16,17,15,16,23,23,0,1,22,23,1,22,1,2,15,23,22,14,15,22,14,22,21,21,22,2,21,2,20,13,14,21,12,13,21,12,21,20,11,12,20,20,2,3,20,3,4,19,20,4,10,20,19,10,19,18,11,20,10,5,19,4,18,19,5,18,5,6,7,18,6,9,10,18,8,9,18,7,8,18],"vertices":[3,49,15.63,-10.29,0.029,50,8.48,-7.41,0.56084,51,2.28,-7.35,0.41016,3,49,11.01,-7.97,0.33042,50,3.31,-7.25,0.61598,51,-2.15,-10.02,0.0536,3,48,15.02,-6.84,0.04512,49,4.71,-6.79,0.8836,50,-2.9,-8.82,0.07129,3,47,19.6,-7.03,0.05267,48,8.02,-8.31,0.59855,49,-2.27,-8.33,0.34878,3,47,12.28,-8.55,0.51912,48,0.55,-8.73,0.46363,49,-9.74,-8.83,0.01725,2,47,3.38,-7.3,0.99781,48,-8.06,-6.18,0.00219,1,47,-4.09,-5.53,1,1,47,-5.51,-0.98,1,1,47,-3.38,2.62,1,2,47,4.14,5.42,0.94138,48,-5.42,6.29,0.05862,3,47,10.72,7.86,0.28481,48,1.45,7.74,0.65932,49,-9.01,7.64,0.05587,3,47,18.71,10.84,5.3E-4,48,9.8,9.49,0.37354,49,-0.68,9.48,0.62593,3,48,16.55,10.9,0.03841,49,6.05,10.97,0.9375,50,-9.13,7.86,0.02409,2,49,14.18,7.88,0.48526,50,-0.46,8.47,0.51474,2,49,19.63,3.57,0.02819,50,6.3,6.84,0.97181,2,50,10.77,4.1,0.85454,51,-2.05,3.56,0.14546,1,51,7.58,0.08,1,3,49,18.73,-12.12,7.7E-4,50,12.07,-7.78,0.26191,51,5.49,-5.71,0.73732,1,47,3.39,-0.48,1,1,48,1.14,-0.53,1,2,48,9.07,0.75,0.92043,49,-1.32,0.74,0.07957,1,49,7.77,1.46,1,1,50,4.54,0.46,1,2,50,10.04,-1.18,0.63553,51,0.21,-1.27,0.36447],"hull":18,"edges":[30,32,30,28,28,26,26,24,22,24,20,22,18,20,16,18,16,14,14,12,12,10,10,8,8,6,6,4,4,2,2,0,32,34,0,34,14,36,36,38,38,40,40,42,42,44,44,46,46,32],"width":47,"height":25}},"017_fish_G2_fadai01":{"017_fish_G2_fadai01":{"x":-7.76,"y":-2.77,"rotation":-90,"width":62,"height":23}},"017_fish_G2_fadai02":{"017_fish_G2_fadai02":{"x":11.27,"y":-3.17,"rotation":-139.33,"width":21,"height":24}},"017_fish_G2_fadai03":{"017_fish_G2_fadai03":{"x":9.82,"y":-0.79,"rotation":-60.15,"width":16,"height":20}},"017_fish_G2_hair03":{"017_fish_G2_hair03":{"type":"mesh","uvs":[1,0.19752,0.91381,0.36507,0.79587,0.50748,0.63284,0.67084,0.47328,0.7965,0.32413,0.90959,0.1715,1,0.06397,1,0,0.87608,0,0.62476,0.14375,0.4991,0.116,0.36088,0.20966,0.29805,0.34147,0.43627,0.45594,0.41533,0.57041,0.33156,0.69181,0.17239,0.77853,0,1,0,0.86821,0.12966,0.76955,0.28366,0.63721,0.43766,0.53374,0.53936,0.40621,0.65268,0.2498,0.72532,0.10543,0.80668],"triangles":[5,6,25,6,7,25,7,8,25,25,24,5,8,9,25,25,9,24,4,24,23,4,5,24,4,23,3,9,10,24,24,10,23,10,13,23,22,23,13,10,12,13,10,11,12,23,22,3,3,22,21,22,13,14,22,14,21,3,21,2,21,20,2,14,15,21,21,15,20,2,20,1,20,19,1,1,19,0,15,16,20,20,16,19,19,18,0,16,17,19,19,17,18],"vertices":[1,54,-3.09,7.91,1,2,54,7.37,9.48,0.89518,55,-5.72,9,0.10482,3,54,18.13,8.6,0.12244,55,5.07,9.09,0.87207,56,-9.34,7.97,0.00549,3,55,18.73,7.93,0.12408,56,4.36,8.56,0.87525,57,-11.31,6,6.7E-4,3,56,16.66,7.66,0.31233,57,0.83,8.11,0.68763,58,-12.67,7.94,4.0E-5,2,57,12.1,9.86,0.61604,58,-1.43,9.84,0.38396,2,57,23.09,10.4,0.01842,58,9.55,10.53,0.98158,1,58,15.98,7.87,1,1,58,17.26,0.15,1,3,56,35.47,-18.21,2.4E-4,57,25.33,-12.46,0.12838,58,12.1,-12.3,0.87138,3,56,23.99,-17.93,0.06375,57,14.12,-14.97,0.67616,58,0.93,-14.96,0.2601,3,56,20.93,-24.92,0.10139,57,12.84,-22.48,0.83629,58,-0.25,-22.49,0.06232,3,56,14.07,-23.93,0.11973,57,5.95,-23.18,0.84332,58,-7.14,-23.28,0.03695,4,55,23.36,-14.25,5.5E-4,56,11.76,-12.87,0.37048,57,1.04,-13,0.62059,58,-12.18,-13.17,0.00839,3,55,17.29,-9.86,0.11363,56,5.18,-9.28,0.76027,57,-6.21,-11.1,0.1261,4,54,20.39,-8.62,0.01548,55,8.86,-7.86,0.82277,56,-3.43,-8.36,0.16146,57,-14.79,-12.3,2.9E-4,2,54,8.8,-8.16,0.78926,55,-2.72,-8.44,0.21074,1,54,-1.87,-9.87,1,1,54,-11.16,1.05,1,1,54,-0.34,-0.94,1,1,54,10.09,-0.46,1,2,55,9.77,-0.78,0.99318,56,-3.43,-1.22,0.00682,3,55,18.37,-1.59,0.00323,56,5.2,-0.94,0.9942,57,-8.21,-3.01,0.00258,2,56,15.45,-1.1,0.03182,57,1.78,-0.69,0.96818,3,56,25.86,-4.13,8.8E-4,57,12.61,-1.12,0.86626,58,-0.77,-1.13,0.13286,2,57,22.92,-0.8,0.00235,58,9.54,-0.68,0.99765],"hull":19,"edges":[34,36,34,32,32,30,30,28,28,26,26,24,24,22,22,20,20,18,16,18,16,14,12,14,12,10,10,8,8,6,6,4,4,2,0,36,2,0,36,38,38,40,40,42,42,44,44,46,46,48,48,50,50,16,20,26],"width":64,"height":53},"017_fish_G3_hair03":{"type":"mesh","uvs":[0.91896,0.07311,1,0.13907,0.95934,0.29107,0.84296,0.43733,0.72659,0.57213,0.58646,0.69831,0.44159,0.81877,0.31097,0.91628,0.16847,1,0.08534,1,0,0.84171,0,0.60654,0.10114,0.58192,0.23022,0.54631,0.15897,0.48322,0.11859,0.37137,0.20409,0.30541,0.27534,0.38571,0.34659,0.44594,0.45584,0.4316,0.56034,0.35416,0.64821,0.24232,0.71946,0.13047,0.78834,0,0.85246,0,0.8244,0.1937,0.73249,0.34385,0.62437,0.45483,0.51083,0.55929,0.38379,0.65068,0.26215,0.70617,0.1351,0.75513],"triangles":[31,12,30,11,12,31,10,11,31,31,30,7,9,10,31,8,9,31,7,8,31,17,14,15,17,15,16,13,14,17,13,17,18,28,29,18,13,18,29,30,13,29,12,13,30,6,29,5,30,29,6,7,30,6,28,19,27,28,18,19,5,28,4,29,28,5,26,21,25,20,21,26,3,26,2,27,20,26,19,20,27,3,4,27,3,27,26,28,27,4,25,23,24,25,24,0,25,0,1,22,23,25,2,25,1,25,21,22,26,25,2],"vertices":[1,54,-4.88,-0.38,1,1,54,-5.58,5.9,1,2,54,2.33,9.17,0.99878,55,-10.71,8.25,0.00122,2,54,13.18,8.51,0.48079,55,0.16,8.56,0.51921,3,54,23.57,7.45,0.00104,55,10.6,8.43,0.85074,56,-3.77,8.02,0.14822,3,55,21.8,6.89,0.01741,56,7.54,7.91,0.96631,57,-8.08,6.14,0.01627,3,56,18.91,7.37,0.09542,57,3.09,8.36,0.89766,58,-10.42,8.23,0.00692,2,57,12.92,9.82,0.52645,58,-0.6,9.82,0.47355,2,57,23.17,10.3,0.01743,58,9.63,10.43,0.98257,1,58,14.6,8.37,1,1,58,16.46,-1.58,1,2,57,24.85,-13.38,0.00959,58,11.63,-13.23,0.99041,3,56,28.76,-16.07,0.0012,57,18.31,-12.01,0.14075,58,5.08,-11.94,0.85805,3,56,20.96,-12.53,0.1004,57,9.88,-10.46,0.75236,58,-3.37,-10.5,0.14725,3,56,22.58,-18.02,0.13155,57,12.78,-15.39,0.85699,58,-0.41,-15.39,0.01146,2,56,21.03,-24.37,0.12773,57,12.81,-21.93,0.87227,2,56,14.49,-23.83,0.13442,57,6.33,-22.99,0.86558,3,56,13.42,-17.62,0.17964,57,3.8,-17.21,0.81968,58,-9.37,-17.34,6.9E-4,3,56,11.71,-12.26,0.39025,57,0.84,-12.42,0.60919,58,-12.39,-12.59,5.7E-4,3,55,17.81,-9.23,0.06574,56,5.61,-8.59,0.81938,57,-5.96,-10.33,0.11488,3,54,21.64,-8.31,0.00244,55,10.07,-7.44,0.73871,56,-2.28,-7.8,0.25885,3,54,13.38,-7.86,0.36823,55,1.82,-7.73,0.63169,56,-10.44,-9.12,7.0E-5,2,54,5.83,-8.23,0.95556,55,-5.68,-8.77,0.04444,1,54,-2.39,-9.36,1,1,54,-5.07,-6.2,1,1,54,4.01,-0.86,1,2,54,14,-0.18,1.5E-4,55,1.74,-0.03,0.99985,2,55,10.9,-0.69,0.99193,56,-2.31,-0.99,0.00807,3,55,20.07,-1.85,4.6E-4,56,6.92,-0.99,0.99585,57,-6.52,-2.64,0.00369,2,56,16.43,-2.06,0.03886,57,2.96,-1.39,0.96114,3,56,24.5,-4.46,0.00223,57,11.37,-1.77,0.91144,58,-2,-1.8,0.08634,2,57,19.96,-2.61,0.00599,58,6.6,-2.52,0.99401],"hull":25,"edges":[46,44,44,42,42,40,40,38,38,36,36,34,34,32,32,30,30,28,28,26,26,24,24,22,16,14,14,12,12,10,10,8,8,6,6,4,4,2,2,0,46,48,0,48,20,22,16,18,20,18,0,50,50,52,52,54,54,56,56,58,58,60,60,62,62,20],"width":64,"height":53}},"017_fish_G3_bian":{"017_fish_G3_bian":{"x":9.28,"y":-0.41,"rotation":-44.04,"width":31,"height":30}},"017_fish_G3_bian01":{"017_fish_G3_bian01":{"x":10.99,"y":-0.56,"rotation":155.27,"width":23,"height":11}},"017_fish_G3_bian_eye":{"017_fish_G3_bian_eye":{"y":0.28,"rotation":-40.17,"width":4,"height":4}},"017_fish_G3_bian_stick":{"017_fish_G3_bian_stick":{"x":6.8,"y":0.26,"rotation":-37.83,"width":14,"height":11}},"017_fish_G3_cap01":{"017_fish_G3_cap01":{"x":10.58,"y":-6.47,"rotation":-140.01,"width":28,"height":43}},"017_fish_G3_cap02":{"017_fish_G3_cap02":{"x":10.32,"y":-1.35,"rotation":-90,"width":85,"height":49}},"017_fish_G3_glass":{"017_fish_G3_glass":{"x":-0.77,"y":1.47,"rotation":-90,"width":63,"height":32}},"017_fish_G3_glass_L01":{"017_fish_G3_glass_L01":{"x":3.28,"y":4.34,"rotation":-90,"width":14,"height":15},"017_fish_G3_glass_L02":{"x":0.66,"y":0.74,"rotation":-90,"width":17,"height":15},"017_fish_G3_glass_L03":{"x":-3.44,"y":-5.16,"rotation":-90,"width":11,"height":13}},"017_fish_G3_glass_R01":{"017_fish_G3_glass_R01":{"x":-4.34,"y":2.95,"width":13,"height":13},"017_fish_G3_glass_R02":{"x":-0.57,"y":-0.49,"width":15,"height":16},"017_fish_G3_glass_R03":{"x":5.32,"y":-2.62,"width":11,"height":13}},"017_fish_G3_hand_L":{"017_fish_G3_hand_L":{"x":16.13,"y":0.85,"rotation":-170.27,"width":38,"height":27}},"017_fish_G3_water":{"017_fish_G3_water":{"x":5.1,"y":-0.16,"rotation":-162.33,"width":12,"height":7}}}},"animations":{"16_fish_G1_move":{"slots":{"001_fish_G1_body":{"attachment":[{"time":0,"name":"017_fish_G3_head"}]},"005_fish_G1_eye":{"attachment":[{"time":0,"name":"017_fish_G2_eye"}]},"012_fish_G1_hand_R":{"attachment":[{"time":0,"name":"017_fish_G3_hand_R"},{"time":0.4,"name":"017_fish_G3_hand_R"}]},"014_fish_G1_leg":{"attachment":[{"time":0,"name":"017_fish_G1_leg"}]},"014_fish_G2_eye_L":{"attachment":[{"time":0,"name":"017_fish_G2_eye_L"},{"time":0.4,"name":"017_fish_G2_eye_L"}]},"014_fish_G2_eye_R":{"attachment":[{"time":0,"name":"017_fish_G2_eye_R"},{"time":0.4,"name":"017_fish_G2_eye_R"}]},"017_fish_G1_body":{"attachment":[{"time":0,"name":"017_fish_G1_body"}]},"017_fish_G1_hair01":{"attachment":[{"time":0,"name":"017_fish_G1_hair01"}]},"017_fish_G1_hair02":{"attachment":[{"time":0,"name":"017_fish_G1_hair02"}]},"017_fish_G1_hair03":{"attachment":[{"time":0,"name":"017_fish_G1_hair03"}]},"017_fish_G1_mouth":{"attachment":[{"time":0,"name":"017_fish_G1_mouth"}]},"017_fish_G2_ear":{"attachment":[{"time":0,"name":"017_fish_G2_ear"}]},"017_fish_G3_hand_L":{"attachment":[{"time":0,"name":"017_fish_G3_hand_L"},{"time":0.4,"name":"017_fish_G3_hand_L"}]}},"bones":{"001_fish_G1_body":{"translate":[{"time":0,"x":0,"y":-0.94},{"time":0.1,"x":0,"y":-1.92},{"time":0.3,"x":0,"y":0.04},{"time":0.4,"x":0,"y":-0.94}],"scale":[{"time":0,"x":1.055,"y":1.025},{"time":0.1,"x":0.995,"y":1.056},{"time":0.3,"x":1.114,"y":0.994},{"time":0.4,"x":1.055,"y":1.025}]},"001_fish_G1_teeth_D":{"translate":[{"time":0,"x":-2.21,"y":0},{"time":0.1,"x":2.09,"y":0},{"time":0.2,"x":-2.21,"y":0},{"time":0.3,"x":2.09,"y":0},{"time":0.4,"x":-2.21,"y":0}]},"001_fish_G1_body2":{"scale":[{"time":0,"x":1.485,"y":1},{"time":0.1,"x":0.655,"y":1},{"time":0.2,"x":1.485,"y":1},{"time":0.3,"x":0.655,"y":1},{"time":0.4,"x":1.485,"y":1}]},"001_fish_G1_teeth_U":{"translate":[{"time":0,"x":-3.93,"y":0},{"time":0.1,"x":-2.87,"y":0},{"time":0.2,"x":-4.83,"y":0},{"time":0.3,"x":-2.87,"y":0},{"time":0.4,"x":-3.93,"y":0}],"scale":[{"time":0,"x":1,"y":1},{"time":0.1,"x":0.868,"y":1},{"time":0.2,"x":1,"y":1},{"time":0.3,"x":0.868,"y":1},{"time":0.4,"x":1,"y":1}]},"004_fish_G1_body":{"translate":[{"time":0,"x":0,"y":-3.92},{"time":0.1,"x":0,"y":-3.17},{"time":0.4,"x":0,"y":-3.92}],"scale":[{"time":0,"x":1,"y":1.086},{"time":0.1,"x":1,"y":0.865},{"time":0.4,"x":1,"y":1.086}]},"014_fish_G2_eye_L":{"translate":[{"time":0,"x":5.21,"y":-13.46},{"time":0.2,"x":11.16,"y":-13.46},{"time":0.4,"x":5.21,"y":-13.46}]},"014_fish_G1_leg":{"rotate":[{"time":0,"angle":-0.75},{"time":0.1,"angle":4.37},{"time":0.3,"angle":-5.87},{"time":0.4,"angle":-0.75}],"translate":[{"time":0,"x":-5.21,"y":-4.84},{"time":0.1,"x":-8.75,"y":-0.62},{"time":0.3,"x":-1.68,"y":-9.05},{"time":0.4,"x":-5.21,"y":-4.84}]},"012_fish_G1_hand_R":{"rotate":[{"time":0,"angle":-28.41},{"time":0.2,"angle":6.21},{"time":0.4,"angle":-28.41}],"translate":[{"time":0,"x":14.95,"y":-15.41,"curve":"stepped"},{"time":0.4,"x":14.95,"y":-15.41}]},"bone":{"translate":[{"time":0,"x":0,"y":8.32}]},"014_fish_G2_eye_R":{"translate":[{"time":0,"x":0.24,"y":-4.39},{"time":0.2,"x":6.19,"y":-4.39},{"time":0.4,"x":0.24,"y":-4.39}]},"001_fish_G1_eye_L":{"scale":[{"time":0,"x":0.594,"y":1},{"time":0.1,"x":1.546,"y":1},{"time":0.4,"x":0.594,"y":1}]},"017_fish_G2_ear":{"rotate":[{"time":0,"angle":15.81},{"time":0.2,"angle":-13.62},{"time":0.4,"angle":15.81}]},"017_fish_G1_hair02":{"rotate":[{"time":0,"angle":-4.17},{"time":0.0667,"angle":4.55},{"time":0.2667,"angle":-21.61},{"time":0.4,"angle":-4.17}]},"017_fish_G1_hair01":{"rotate":[{"time":0,"angle":-7.13},{"time":0.0667,"angle":-13.02},{"time":0.2667,"angle":4.66},{"time":0.4,"angle":-7.13}]},"004_fish_G1_hand":{"rotate":[{"time":0,"angle":-33.17},{"time":0.2,"angle":-67.74},{"time":0.4,"angle":-33.17}],"translate":[{"time":0,"x":2.06,"y":-32.36}]},"017_fish_G1_hair1":{"rotate":[{"time":0,"angle":5.85},{"time":0.0667,"angle":2.6},{"time":0.1333,"angle":-0.64},{"time":0.3333,"angle":9.09},{"time":0.4,"angle":5.85}]},"017_fish_G1_hair2":{"rotate":[{"time":0,"angle":19.18},{"time":0.0667,"angle":12.57},{"time":0.2,"angle":-0.64},{"time":0.4,"angle":19.18}]},"017_fish_G1_hair11":{"rotate":[{"time":0,"angle":4.12},{"time":0.0667,"angle":17.81},{"time":0.2667,"angle":-23.25},{"time":0.4,"angle":4.12}]},"017_fish_G1_hair15":{"rotate":[{"time":0,"angle":-6.67},{"time":0.0667,"angle":-12.71},{"time":0.1333,"angle":-18.74},{"time":0.3333,"angle":-0.64},{"time":0.4,"angle":-6.67}]},"017_fish_G1_hair12":{"rotate":[{"time":0,"angle":-12.89},{"time":0.0667,"angle":-4.17},{"time":0.1333,"angle":4.55},{"time":0.3333,"angle":-21.61},{"time":0.4,"angle":-12.89}]},"017_fish_G1_hair6":{"rotate":[{"time":0,"angle":-0.5},{"time":0.2,"angle":6.34},{"time":0.4,"angle":-0.5}]},"017_fish_G1_hair7":{"rotate":[{"time":0,"angle":1.22},{"time":0.0667,"angle":-4.17},{"time":0.2667,"angle":12},{"time":0.4,"angle":1.22}]},"017_fish_G1_hair8":{"rotate":[{"time":0,"angle":13.6},{"time":0.1333,"angle":-5.14},{"time":0.3333,"angle":22.97},{"time":0.4,"angle":13.6}]},"017_fish_G1_hair3":{"rotate":[{"time":0,"angle":3.55},{"time":0.2,"angle":-8.4},{"time":0.4,"angle":3.55}]},"017_fish_G1_hair4":{"rotate":[{"time":0,"angle":-0.43},{"time":0.0667,"angle":3.55},{"time":0.2667,"angle":-8.4},{"time":0.4,"angle":-0.43}]},"017_fish_G1_hair5":{"rotate":[{"time":0,"angle":-4.41},{"time":0.1333,"angle":3.55},{"time":0.3333,"angle":-8.4},{"time":0.4,"angle":-4.41}]},"017_fish_G1_hair9":{"rotate":[{"time":0,"angle":7.4},{"time":0.2,"angle":-22.8},{"time":0.4,"angle":7.4}]},"017_fish_G1_hair10":{"rotate":[{"time":0,"angle":346.73},{"time":0.2,"angle":20.54},{"time":0.4,"angle":346.73}]}}},"16_fish_G2_move":{"slots":{"001_fish_G1_body":{"attachment":[{"time":0,"name":"017_fish_G3_head"}]},"005_fish_G1_eye":{"attachment":[{"time":0,"name":"017_fish_G2_eye"}]},"012_fish_G1_hand_R":{"attachment":[{"time":0,"name":"017_fish_G3_hand_R"},{"time":0.4,"name":"017_fish_G3_hand_R"}]},"014_fish_G1_leg":{"attachment":[{"time":0,"name":"017_fish_G3_leg"},{"time":0.4,"name":"017_fish_G3_leg"}]},"014_fish_G2_eye_L":{"attachment":[{"time":0,"name":"017_fish_G2_eye_L"},{"time":0.4,"name":"017_fish_G2_eye_L"}]},"014_fish_G2_eye_R":{"attachment":[{"time":0,"name":"017_fish_G2_eye_R"},{"time":0.4,"name":"017_fish_G2_eye_R"}]},"017_fish_G1_body":{"attachment":[{"time":0,"name":"017_fish_G3_body"}]},"017_fish_G1_hair01":{"attachment":[{"time":0,"name":"017_fish_G2_hair02"}]},"017_fish_G1_hair02":{"attachment":[{"time":0,"name":"017_fish_G2_hair01"}]},"017_fish_G1_hair03":{"attachment":[{"time":0,"name":"017_fish_G2_hair04"}]},"017_fish_G1_mouth":{"attachment":[{"time":0,"name":"017_fish_G2_mouth"}]},"017_fish_G2_ear":{"attachment":[{"time":0,"name":"017_fish_G2_ear"}]},"017_fish_G2_fadai01":{"attachment":[{"time":0,"name":"017_fish_G2_fadai01"}]},"017_fish_G2_fadai02":{"attachment":[{"time":0,"name":"017_fish_G2_fadai02"},{"time":0.4,"name":"017_fish_G2_fadai02"}]},"017_fish_G2_fadai03":{"attachment":[{"time":0,"name":"017_fish_G2_fadai03"},{"time":0.4,"name":"017_fish_G2_fadai03"}]},"017_fish_G2_hair03":{"attachment":[{"time":0,"name":"017_fish_G2_hair03"},{"time":0.4,"name":"017_fish_G2_hair03"}]},"017_fish_G3_hand_L":{"attachment":[{"time":0,"name":"017_fish_G3_hand_L"},{"time":0.4,"name":"017_fish_G3_hand_L"}]}},"bones":{"001_fish_G1_body":{"translate":[{"time":0,"x":0,"y":-0.94},{"time":0.1,"x":0,"y":-1.92},{"time":0.3,"x":0,"y":0.04},{"time":0.4,"x":0,"y":-0.94}],"scale":[{"time":0,"x":1.055,"y":1.025},{"time":0.1,"x":0.995,"y":1.056},{"time":0.3,"x":1.114,"y":0.994},{"time":0.4,"x":1.055,"y":1.025}]},"001_fish_G1_teeth_D":{"translate":[{"time":0,"x":-2.21,"y":0},{"time":0.1,"x":2.09,"y":0},{"time":0.2,"x":-2.21,"y":0},{"time":0.3,"x":2.09,"y":0},{"time":0.4,"x":-2.21,"y":0}]},"001_fish_G1_body2":{"scale":[{"time":0,"x":1.485,"y":1},{"time":0.1,"x":0.655,"y":1},{"time":0.2,"x":1.485,"y":1},{"time":0.3,"x":0.655,"y":1},{"time":0.4,"x":1.485,"y":1}]},"001_fish_G1_teeth_U":{"translate":[{"time":0,"x":-3.93,"y":0},{"time":0.1,"x":-2.87,"y":0},{"time":0.2,"x":-4.83,"y":0},{"time":0.3,"x":-2.87,"y":0},{"time":0.4,"x":-3.93,"y":0}],"scale":[{"time":0,"x":1,"y":1},{"time":0.1,"x":0.868,"y":1},{"time":0.2,"x":1,"y":1},{"time":0.3,"x":0.868,"y":1},{"time":0.4,"x":1,"y":1}]},"004_fish_G1_body":{"translate":[{"time":0,"x":0,"y":-3.92},{"time":0.1,"x":0,"y":-3.17},{"time":0.4,"x":0,"y":-3.92}],"scale":[{"time":0,"x":1,"y":1.086},{"time":0.1,"x":1,"y":0.865},{"time":0.4,"x":1,"y":1.086}]},"014_fish_G2_eye_L":{"translate":[{"time":0,"x":5.21,"y":-13.46},{"time":0.2,"x":11.16,"y":-13.46},{"time":0.4,"x":5.21,"y":-13.46}]},"014_fish_G1_leg":{"rotate":[{"time":0,"angle":-1.74},{"time":0.1,"angle":-17.16},{"time":0.3,"angle":13.68},{"time":0.4,"angle":-1.74}],"translate":[{"time":0,"x":7.82,"y":-15.59},{"time":0.1,"x":8.54,"y":-18.2},{"time":0.3,"x":7.11,"y":-12.97},{"time":0.4,"x":7.82,"y":-15.59}]},"012_fish_G1_hand_R":{"rotate":[{"time":0,"angle":-28.41},{"time":0.2,"angle":6.21},{"time":0.4,"angle":-28.41}],"translate":[{"time":0,"x":14.95,"y":-15.41,"curve":"stepped"},{"time":0.4,"x":14.95,"y":-15.41}]},"bone":{"translate":[{"time":0,"x":0,"y":8.32}]},"014_fish_G2_eye_R":{"translate":[{"time":0,"x":0.24,"y":-4.39},{"time":0.2,"x":6.19,"y":-4.39},{"time":0.4,"x":0.24,"y":-4.39}]},"001_fish_G1_eye_L":{"scale":[{"time":0,"x":0.594,"y":1},{"time":0.1,"x":1.14,"y":1},{"time":0.4,"x":0.594,"y":1}]},"017_fish_G2_ear":{"rotate":[{"time":0,"angle":15.81},{"time":0.2,"angle":-13.62},{"time":0.4,"angle":15.81}]},"017_fish_G1_hair02":{"rotate":[{"time":0,"angle":-9.11},{"time":0.0667,"angle":-4.56},{"time":0.1333,"angle":0},{"time":0.3333,"angle":-13.67},{"time":0.4,"angle":-9.11}]},"017_fish_G1_hair01":{"rotate":[{"time":0,"angle":-7.13},{"time":0.0667,"angle":-13.02},{"time":0.2667,"angle":4.66},{"time":0.4,"angle":-7.13}],"translate":[{"time":0,"x":0,"y":-1.35}]},"004_fish_G1_hand":{"rotate":[{"time":0,"angle":-33.17},{"time":0.2,"angle":-67.74},{"time":0.4,"angle":-33.17}],"translate":[{"time":0,"x":3.22,"y":-24.6}]},"017_fish_G1_hair1":{"rotate":[{"time":0,"angle":5.85},{"time":0.0667,"angle":2.6},{"time":0.1333,"angle":-0.64},{"time":0.3333,"angle":9.09},{"time":0.4,"angle":5.85}]},"017_fish_G1_hair2":{"rotate":[{"time":0,"angle":19.18},{"time":0.0667,"angle":12.57},{"time":0.2,"angle":-0.64},{"time":0.4,"angle":19.18}]},"017_fish_G1_hair11":{"rotate":[{"time":0,"angle":4.12},{"time":0.0667,"angle":17.81},{"time":0.2667,"angle":-23.25},{"time":0.4,"angle":4.12}]},"017_fish_G1_hair15":{"rotate":[{"time":0,"angle":-6.67},{"time":0.0667,"angle":-12.71},{"time":0.1333,"angle":-18.74},{"time":0.3333,"angle":-0.64},{"time":0.4,"angle":-6.67}]},"017_fish_G1_hair6":{"rotate":[{"time":0,"angle":-0.5},{"time":0.2,"angle":6.34},{"time":0.4,"angle":-0.5}]},"017_fish_G1_hair7":{"rotate":[{"time":0,"angle":1.22},{"time":0.0667,"angle":-4.17},{"time":0.2667,"angle":12},{"time":0.4,"angle":1.22}]},"017_fish_G1_hair8":{"rotate":[{"time":0,"angle":13.6},{"time":0.1333,"angle":-5.14},{"time":0.3333,"angle":22.97},{"time":0.4,"angle":13.6}]},"017_fish_G1_hair3":{"rotate":[{"time":0,"angle":3.55},{"time":0.2,"angle":-8.4},{"time":0.4,"angle":3.55}]},"017_fish_G1_hair4":{"rotate":[{"time":0,"angle":-0.43},{"time":0.0667,"angle":3.55},{"time":0.2667,"angle":-8.4},{"time":0.4,"angle":-0.43}]},"017_fish_G1_hair5":{"rotate":[{"time":0,"angle":-4.41},{"time":0.1333,"angle":3.55},{"time":0.3333,"angle":-8.4},{"time":0.4,"angle":-4.41}]},"017_fish_G1_hair9":{"rotate":[{"time":0,"angle":7.4},{"time":0.2,"angle":-22.8},{"time":0.4,"angle":7.4}]},"017_fish_G1_hair10":{"rotate":[{"time":0,"angle":346.73},{"time":0.2,"angle":20.54},{"time":0.4,"angle":346.73}]},"017_fish_G2_hair03":{"rotate":[{"time":0,"angle":-12.66},{"time":0.1333,"angle":5.32},{"time":0.3333,"angle":-21.65},{"time":0.4,"angle":-12.66}]},"017_fish_G2_fadai03":{"rotate":[{"time":0,"angle":-9.61},{"time":0.2,"angle":13.65},{"time":0.4,"angle":-9.61}]},"017_fish_G2_fadai02":{"rotate":[{"time":0,"angle":11.22},{"time":0.2,"angle":-21.46},{"time":0.4,"angle":11.22}]},"017_fish_G1_hair16":{"rotate":[{"time":0,"angle":-5.88},{"time":0.2,"angle":-21.79},{"time":0.4,"angle":-5.88}]},"017_fish_G1_hair17":{"rotate":[{"time":0,"angle":-4.81},{"time":0.0667,"angle":0},{"time":0.2667,"angle":-14.43},{"time":0.4,"angle":-4.81}]},"017_fish_G1_hair18":{"rotate":[{"time":0,"angle":-11.16},{"time":0.1333,"angle":0},{"time":0.3333,"angle":-16.75},{"time":0.4,"angle":-11.16}]},"017_fish_G1_hair19":{"rotate":[{"time":0,"angle":-14.68},{"time":0.2,"angle":0},{"time":0.4,"angle":-14.68}]},"017_fish_G1_hair20":{"rotate":[{"time":0,"angle":5.19},{"time":0.1333,"angle":-13.16},{"time":0.2,"angle":-22.33},{"time":0.4,"angle":5.19}]},"017_fish_G2_hair3":{"rotate":[{"time":0,"angle":-11.11},{"time":0.1333,"angle":-3.26},{"time":0.2,"angle":0.67},{"time":0.4,"angle":-11.11}]},"017_fish_G2_hair4":{"rotate":[{"time":0,"angle":-4.3},{"time":0.0667,"angle":-8.96},{"time":0.1333,"angle":-4.3},{"time":0.2667,"angle":5.02},{"time":0.4,"angle":-4.3}]},"017_fish_G2_hair5":{"rotate":[{"time":0,"angle":2},{"time":0.1333,"angle":-8.44},{"time":0.3333,"angle":7.23},{"time":0.4,"angle":2}]},"017_fish_G2_hair6":{"rotate":[{"time":0,"angle":-16.67},{"time":0.0667,"angle":-24.59},{"time":0.2667,"angle":-0.83},{"time":0.4,"angle":-16.67}]},"017_fish_G1_hair12":{"rotate":[{"time":0,"angle":-17.47},{"time":0.0667,"angle":-10.84},{"time":0.2,"angle":2.44},{"time":0.4,"angle":-17.47}]},"017_fish_G1_hair13":{"rotate":[{"time":0,"angle":2.33},{"time":0.0667,"angle":-5.2},{"time":0.2667,"angle":17.38},{"time":0.4,"angle":2.33}]},"017_fish_G1_hair14":{"rotate":[{"time":0,"angle":7.17},{"time":0.0667,"angle":0.99},{"time":0.1333,"angle":-5.2},{"time":0.3333,"angle":13.36},{"time":0.4,"angle":7.17}]}}},"16_fish_G3_move":{"slots":{"001_fish_G1_body":{"attachment":[{"time":0,"name":"017_fish_G3_head"},{"time":0.4,"name":"017_fish_G3_head"}]},"001_fish_G1_mouth_back":{"attachment":[{"time":0,"name":"017_fish_G3_mouth_back"},{"time":0.4,"name":"017_fish_G3_mouth_back"}]},"001_fish_G1_teeth_D":{"attachment":[{"time":0,"name":"017_fish_G3_teeth_d"},{"time":0.4,"name":"017_fish_G3_teeth_d"},{"time":0.8,"name":"017_fish_G3_teeth_d"}]},"001_fish_G1_teeth_U":{"attachment":[{"time":0,"name":"017_fish_G3_teeth_u"},{"time":0.4,"name":"017_fish_G3_teeth_u"},{"time":0.8,"name":"017_fish_G3_teeth_u"}]},"001_fish_G2_mouth":{"attachment":[{"time":0,"name":"017_fish_G3_mouth"},{"time":0.4,"name":"017_fish_G3_mouth"}]},"012_fish_G1_hand_R":{"attachment":[{"time":0,"name":"017_fish_G3_hand_R"},{"time":0.4,"name":"017_fish_G3_hand_R"}]},"014_fish_G1_leg":{"attachment":[{"time":0,"name":"017_fish_G3_leg"},{"time":0.4,"name":"017_fish_G3_leg"}]},"017_fish_G1_body":{"attachment":[{"time":0,"name":"017_fish_G3_body"},{"time":0.4,"name":"017_fish_G3_body"}]},"017_fish_G1_hair01":{"attachment":[{"time":0,"name":"017_fish_G3_hair02"},{"time":0.4,"name":"017_fish_G3_hair02"}]},"017_fish_G1_hair02":{"attachment":[{"time":0,"name":"017_fish_G3_hair01"},{"time":0.4,"name":"017_fish_G3_hair01"}]},"017_fish_G1_hair03":{"attachment":[{"time":0,"name":"017_fish_G3_hair04"},{"time":0.4,"name":"017_fish_G3_hair04"}]},"017_fish_G2_ear":{"attachment":[{"time":0,"name":"017_fish_G3_ear"},{"time":0.4,"name":"017_fish_G3_ear"}]},"017_fish_G2_hair03":{"attachment":[{"time":0,"name":"017_fish_G3_hair03"},{"time":0.4,"name":"017_fish_G3_hair03"}]},"017_fish_G3_bian":{"attachment":[{"time":0,"name":"017_fish_G3_bian"},{"time":0.4,"name":"017_fish_G3_bian"}]},"017_fish_G3_bian01":{"attachment":[{"time":0.4,"name":"017_fish_G3_bian01"}],"attachment":[{"time":0,"name":"017_fish_G3_bian01"},{"time":0.4,"name":"017_fish_G3_bian01"}]},"017_fish_G3_bian_eye":{"attachment":[{"time":0,"name":"017_fish_G3_bian_eye"},{"time":0.4,"name":"017_fish_G3_bian_eye"}]},"017_fish_G3_bian_stick":{"attachment":[{"time":0,"name":"017_fish_G3_bian_stick"},{"time":0.4,"name":"017_fish_G3_bian_stick"}]},"017_fish_G3_cap01":{"attachment":[{"time":0,"name":"017_fish_G3_cap01"},{"time":0.4,"name":"017_fish_G3_cap01"}]},"017_fish_G3_cap02":{"attachment":[{"time":0,"name":"017_fish_G3_cap02"}]},"017_fish_G3_glass":{"attachment":[{"time":0,"name":"017_fish_G3_glass"},{"time":0.4,"name":"017_fish_G3_glass"}]},"017_fish_G3_glass_L01":{"attachment":[{"time":0.1333,"name":"017_fish_G3_glass_L01"},{"time":0.2333,"name":"017_fish_G3_glass_L02"},{"time":0.3333,"name":"017_fish_G3_glass_L03"},{"time":0.4333,"name":null}]},"017_fish_G3_glass_R01":{"attachment":[{"time":0.2,"name":"017_fish_G3_glass_R01"},{"time":0.3,"name":"017_fish_G3_glass_R02"},{"time":0.4,"name":"017_fish_G3_glass_R03"},{"time":0.5,"name":null}]},"017_fish_G3_hand_L":{"attachment":[{"time":0,"name":"017_fish_G3_hand_L"}]},"017_fish_G3_water":{"attachment":[{"time":0,"name":"017_fish_G3_water"},{"time":0.4,"name":"017_fish_G3_water"},{"time":0.8,"name":"017_fish_G3_water"}]}},"bones":{"001_fish_G1_body":{"translate":[{"time":0,"x":0,"y":-0.94},{"time":0.1,"x":0,"y":-1.92},{"time":0.3,"x":0,"y":0.04},{"time":0.4,"x":0,"y":-0.94},{"time":0.5,"x":0,"y":-1.92},{"time":0.7,"x":0,"y":0.04},{"time":0.8,"x":0,"y":-0.94}],"scale":[{"time":0,"x":1.055,"y":1.025},{"time":0.1,"x":0.995,"y":1.056},{"time":0.3,"x":1.114,"y":0.994},{"time":0.4,"x":1.055,"y":1.025},{"time":0.5,"x":0.995,"y":1.056},{"time":0.7,"x":1.114,"y":0.994},{"time":0.8,"x":1.055,"y":1.025}]},"001_fish_G1_teeth_D":{"translate":[{"time":0,"x":17.9,"y":14.84},{"time":0.1,"x":14.07,"y":14.84},{"time":0.4,"x":17.9,"y":14.84},{"time":0.5,"x":14.07,"y":14.84},{"time":0.8,"x":17.9,"y":14.84}]},"001_fish_G1_body2":{"translate":[{"time":0,"x":18.92,"y":14.84,"curve":"stepped"},{"time":0.4,"x":18.92,"y":14.84}],"scale":[{"time":0,"x":1.485,"y":1,"curve":"stepped"},{"time":0.4,"x":1.485,"y":1}]},"001_fish_G1_teeth_U":{"translate":[{"time":0,"x":14.39,"y":14.84},{"time":0.1,"x":22.89,"y":14.84},{"time":0.4,"x":14.39,"y":14.84},{"time":0.5,"x":22.89,"y":14.84},{"time":0.8,"x":14.39,"y":14.84}],"scale":[{"time":0,"x":1,"y":1,"curve":"stepped"},{"time":0.4,"x":1,"y":1,"curve":"stepped"},{"time":0.8,"x":1,"y":1}]},"004_fish_G1_body":{"translate":[{"time":0,"x":0,"y":-3.92},{"time":0.1,"x":0,"y":-3.17},{"time":0.4,"x":0,"y":-3.92},{"time":0.5,"x":0,"y":-3.17},{"time":0.8,"x":0,"y":-3.92}],"scale":[{"time":0,"x":1,"y":1.086},{"time":0.1,"x":1,"y":0.865},{"time":0.4,"x":1,"y":1.086},{"time":0.5,"x":1,"y":0.865},{"time":0.8,"x":1,"y":1.086}]},"014_fish_G1_leg":{"rotate":[{"time":0,"angle":-1.74},{"time":0.1,"angle":-17.16},{"time":0.3,"angle":13.68},{"time":0.4,"angle":-1.74},{"time":0.5,"angle":-17.16},{"time":0.7,"angle":13.68},{"time":0.8,"angle":-1.74}],"translate":[{"time":0,"x":7.82,"y":-15.59},{"time":0.1,"x":8.54,"y":-18.2},{"time":0.3,"x":7.11,"y":-12.97},{"time":0.4,"x":7.82,"y":-15.59},{"time":0.5,"x":8.54,"y":-18.2},{"time":0.7,"x":7.11,"y":-12.97},{"time":0.8,"x":7.82,"y":-15.59}]},"012_fish_G1_hand_R":{"rotate":[{"time":0,"angle":-14.48},{"time":0.2,"angle":-6.17},{"time":0.4,"angle":-14.48},{"time":0.6,"angle":-6.17},{"time":0.8,"angle":-14.48}],"translate":[{"time":0,"x":5.32,"y":-12.96,"curve":"stepped"},{"time":0.4,"x":5.32,"y":-12.96}]},"bone":{"translate":[{"time":0,"x":0,"y":8.32,"curve":"stepped"},{"time":0.4,"x":0,"y":8.32}]},"017_fish_G2_ear":{"rotate":[{"time":0,"angle":8.46},{"time":0.1333,"angle":14.4},{"time":0.3333,"angle":5.48},{"time":0.4,"angle":8.46},{"time":0.5333,"angle":14.4},{"time":0.7333,"angle":5.48},{"time":0.8,"angle":8.46}]},"017_fish_G1_hair02":{"rotate":[{"time":0,"angle":-9.11},{"time":0.0667,"angle":-4.56},{"time":0.1333,"angle":0},{"time":0.3333,"angle":-13.67},{"time":0.4,"angle":-9.11},{"time":0.4667,"angle":-4.56},{"time":0.5333,"angle":0},{"time":0.7333,"angle":-13.67},{"time":0.8,"angle":-9.11}]},"017_fish_G1_hair01":{"rotate":[{"time":0,"angle":-7.13},{"time":0.0667,"angle":-13.02},{"time":0.2667,"angle":4.66},{"time":0.4,"angle":-7.13},{"time":0.4667,"angle":-13.02},{"time":0.6667,"angle":4.66},{"time":0.8,"angle":-7.13}],"translate":[{"time":0,"x":0,"y":-6.59}]},"004_fish_G1_hand":{"rotate":[{"time":0,"angle":-33.17},{"time":0.2,"angle":-67.74},{"time":0.4,"angle":-33.17},{"time":0.6,"angle":-67.74},{"time":0.8,"angle":-33.17}],"translate":[{"time":0,"x":3.22,"y":-24.6}]},"017_fish_G1_hair1":{"rotate":[{"time":0,"angle":5.85},{"time":0.0667,"angle":2.6},{"time":0.1333,"angle":-0.64},{"time":0.3333,"angle":9.09},{"time":0.4,"angle":5.85},{"time":0.4667,"angle":2.6},{"time":0.5333,"angle":-0.64},{"time":0.7333,"angle":9.09},{"time":0.8,"angle":5.85}]},"017_fish_G1_hair2":{"rotate":[{"time":0,"angle":19.18},{"time":0.0667,"angle":12.57},{"time":0.2,"angle":-0.64},{"time":0.4,"angle":19.18},{"time":0.4667,"angle":12.57},{"time":0.6,"angle":-0.64},{"time":0.8,"angle":19.18}]},"017_fish_G1_hair11":{"rotate":[{"time":0,"angle":4.12},{"time":0.0667,"angle":17.81},{"time":0.2667,"angle":-23.25},{"time":0.4,"angle":4.12},{"time":0.4667,"angle":17.81},{"time":0.6667,"angle":-23.25},{"time":0.8,"angle":4.12}]},"017_fish_G1_hair15":{"rotate":[{"time":0,"angle":-6.67},{"time":0.0667,"angle":-12.71},{"time":0.1333,"angle":-18.74},{"time":0.3333,"angle":-0.64},{"time":0.4,"angle":-6.67},{"time":0.4667,"angle":-12.71},{"time":0.5333,"angle":-18.74},{"time":0.7333,"angle":-0.64},{"time":0.8,"angle":-6.67}]},"017_fish_G1_hair6":{"rotate":[{"time":0,"angle":-0.5},{"time":0.2,"angle":6.34},{"time":0.4,"angle":-0.5},{"time":0.6,"angle":6.34},{"time":0.8,"angle":-0.5}]},"017_fish_G1_hair7":{"rotate":[{"time":0,"angle":1.22},{"time":0.0667,"angle":-4.17},{"time":0.2667,"angle":12},{"time":0.4,"angle":1.22},{"time":0.4667,"angle":-4.17},{"time":0.6667,"angle":12},{"time":0.8,"angle":1.22}]},"017_fish_G1_hair8":{"rotate":[{"time":0,"angle":13.6},{"time":0.1333,"angle":-5.14},{"time":0.3333,"angle":22.97},{"time":0.4,"angle":13.6},{"time":0.5333,"angle":-5.14},{"time":0.7333,"angle":22.97},{"time":0.8,"angle":13.6}]},"017_fish_G1_hair3":{"rotate":[{"time":0,"angle":3.55},{"time":0.2,"angle":-8.4},{"time":0.4,"angle":3.55},{"time":0.6,"angle":-8.4},{"time":0.8,"angle":3.55}]},"017_fish_G1_hair4":{"rotate":[{"time":0,"angle":-0.43},{"time":0.0667,"angle":3.55},{"time":0.2667,"angle":-8.4},{"time":0.4,"angle":-0.43},{"time":0.4667,"angle":3.55},{"time":0.6667,"angle":-8.4},{"time":0.8,"angle":-0.43}]},"017_fish_G1_hair5":{"rotate":[{"time":0,"angle":-4.41},{"time":0.1333,"angle":3.55},{"time":0.3333,"angle":-8.4},{"time":0.4,"angle":-4.41},{"time":0.5333,"angle":3.55},{"time":0.7333,"angle":-8.4},{"time":0.8,"angle":-4.41}]},"017_fish_G1_hair9":{"rotate":[{"time":0,"angle":7.4},{"time":0.2,"angle":-22.8},{"time":0.4,"angle":7.4},{"time":0.6,"angle":-22.8},{"time":0.8,"angle":7.4}]},"017_fish_G1_hair10":{"rotate":[{"time":0,"angle":346.73},{"time":0.2,"angle":20.54},{"time":0.4,"angle":346.73},{"time":0.6,"angle":20.54},{"time":0.8,"angle":346.73}]},"017_fish_G2_hair03":{"rotate":[{"time":0,"angle":-12.66},{"time":0.1333,"angle":5.32},{"time":0.3333,"angle":-21.65},{"time":0.4,"angle":-12.66},{"time":0.5333,"angle":5.32},{"time":0.7333,"angle":-21.65},{"time":0.8,"angle":-12.66}]},"017_fish_G1_hair16":{"rotate":[{"time":0,"angle":-5.88},{"time":0.2,"angle":-21.79},{"time":0.4,"angle":-5.88},{"time":0.6,"angle":-21.79},{"time":0.8,"angle":-5.88}]},"017_fish_G1_hair17":{"rotate":[{"time":0,"angle":-4.81},{"time":0.0667,"angle":0},{"time":0.2667,"angle":-14.43},{"time":0.4,"angle":-4.81},{"time":0.4667,"angle":0},{"time":0.6667,"angle":-14.43},{"time":0.8,"angle":-4.81}]},"017_fish_G1_hair18":{"rotate":[{"time":0,"angle":-11.16},{"time":0.1333,"angle":0},{"time":0.3333,"angle":-16.75},{"time":0.4,"angle":-11.16},{"time":0.5333,"angle":0},{"time":0.7333,"angle":-16.75},{"time":0.8,"angle":-11.16}]},"017_fish_G1_hair19":{"rotate":[{"time":0,"angle":-14.68},{"time":0.2,"angle":0},{"time":0.4,"angle":-14.68},{"time":0.6,"angle":0},{"time":0.8,"angle":-14.68}]},"017_fish_G1_hair20":{"rotate":[{"time":0,"angle":5.19},{"time":0.1333,"angle":-13.16},{"time":0.2,"angle":-22.33},{"time":0.4,"angle":5.19},{"time":0.5333,"angle":-13.16},{"time":0.6,"angle":-22.33},{"time":0.8,"angle":5.19}]},"017_fish_G2_hair3":{"rotate":[{"time":0,"angle":-11.11},{"time":0.1333,"angle":-3.26},{"time":0.2,"angle":0.67},{"time":0.4,"angle":-11.11},{"time":0.5333,"angle":-3.26},{"time":0.6,"angle":0.67},{"time":0.8,"angle":-11.11}]},"017_fish_G2_hair4":{"rotate":[{"time":0,"angle":-4.3},{"time":0.0667,"angle":-8.96},{"time":0.1333,"angle":-4.3},{"time":0.2667,"angle":5.02},{"time":0.4,"angle":-4.3},{"time":0.4667,"angle":-8.96},{"time":0.5333,"angle":-4.3},{"time":0.6667,"angle":5.02},{"time":0.8,"angle":-4.3}]},"017_fish_G2_hair5":{"rotate":[{"time":0,"angle":2},{"time":0.1333,"angle":-8.44},{"time":0.3333,"angle":7.23},{"time":0.4,"angle":2},{"time":0.5333,"angle":-8.44},{"time":0.7333,"angle":7.23},{"time":0.8,"angle":2}]},"017_fish_G2_hair6":{"rotate":[{"time":0,"angle":-16.67},{"time":0.0667,"angle":-24.59},{"time":0.2667,"angle":-0.83},{"time":0.4,"angle":-16.67},{"time":0.4667,"angle":-24.59},{"time":0.6667,"angle":-0.83},{"time":0.8,"angle":-16.67}]},"017_fish_G1_hair12":{"rotate":[{"time":0,"angle":-17.47},{"time":0.0667,"angle":-10.84},{"time":0.2,"angle":2.44},{"time":0.4,"angle":-17.47},{"time":0.4667,"angle":-10.84},{"time":0.6,"angle":2.44},{"time":0.8,"angle":-17.47}]},"017_fish_G1_hair13":{"rotate":[{"time":0,"angle":2.33},{"time":0.0667,"angle":-5.2},{"time":0.2667,"angle":17.38},{"time":0.4,"angle":2.33},{"time":0.4667,"angle":-5.2},{"time":0.6667,"angle":17.38},{"time":0.8,"angle":2.33}]},"017_fish_G1_hair14":{"rotate":[{"time":0,"angle":7.17},{"time":0.0667,"angle":0.99},{"time":0.1333,"angle":-5.2},{"time":0.3333,"angle":13.36},{"time":0.4,"angle":7.17},{"time":0.4667,"angle":0.99},{"time":0.5333,"angle":-5.2},{"time":0.7333,"angle":13.36},{"time":0.8,"angle":7.17}]},"005_fish_G1_head03":{"translate":[{"time":0,"x":1.1,"y":-4.87},{"time":0.0667,"x":-1.66,"y":-4.87},{"time":0.2667,"x":6.62,"y":-4.87},{"time":0.4667,"x":-1.66,"y":-4.87},{"time":0.6667,"x":6.62,"y":-4.87},{"time":0.8,"x":1.1,"y":-4.87}]},"017_fish_G3_cap01":{"rotate":[{"time":0,"angle":17.71},{"time":0.2,"angle":-16.79},{"time":0.4,"angle":17.71},{"time":0.6,"angle":-16.79},{"time":0.8,"angle":17.71}]},"017_fish_G3_bian":{"rotate":[{"time":0,"angle":6.07},{"time":0.1333,"angle":-16.13},{"time":0.3333,"angle":17.17},{"time":0.4,"angle":6.07},{"time":0.5333,"angle":-16.13},{"time":0.7333,"angle":17.17},{"time":0.8,"angle":6.07}],"translate":[{"time":0,"x":0.08,"y":0.1},{"time":0.2,"x":20.75,"y":3.01},{"time":0.4,"x":0.08,"y":0.1},{"time":0.6,"x":20.75,"y":3.01},{"time":0.8,"x":0.08,"y":0.1}],"scale":[{"time":0,"x":0.868,"y":1.078},{"time":0.2,"x":1.182,"y":0.962},{"time":0.4,"x":0.868,"y":1.078},{"time":0.6,"x":1.182,"y":0.962},{"time":0.8,"x":0.868,"y":1.078}]},"017_fish_G2_ear2":{"rotate":[{"time":0,"angle":-16.07},{"time":0.0333,"angle":-21.09},{"time":0.1333,"angle":-6.01},{"time":0.2333,"angle":9.08},{"time":0.4,"angle":-16.07},{"time":0.4333,"angle":-21.09},{"time":0.5333,"angle":-6.01},{"time":0.6333,"angle":9.08},{"time":0.8,"angle":-16.07}]},"017_fish_G2_ear3":{"rotate":[{"time":0,"angle":-8.14},{"time":0.0667,"angle":-17.25},{"time":0.1333,"angle":-8.14},{"time":0.2667,"angle":10.08},{"time":0.4,"angle":-8.14},{"time":0.4667,"angle":-17.25},{"time":0.5333,"angle":-8.14},{"time":0.6667,"angle":10.08},{"time":0.8,"angle":-8.14}]},"017_fish_G2_ear4":{"rotate":[{"time":0,"angle":22.42},{"time":0.1333,"angle":-11.06},{"time":0.3333,"angle":39.16},{"time":0.4,"angle":22.42},{"time":0.5333,"angle":-11.06},{"time":0.7333,"angle":39.16},{"time":0.8,"angle":22.42}]},"017_fish_G2_ear5":{"rotate":[{"time":0,"angle":46.03},{"time":0.1333,"angle":12.88},{"time":0.2,"angle":-3.7},{"time":0.4,"angle":46.03},{"time":0.5333,"angle":12.88},{"time":0.6,"angle":-3.7},{"time":0.8,"angle":46.03}]},"017_fish_G3_bian_stick":{"rotate":[{"time":0,"angle":-0.1},{"time":0.0667,"angle":-4.55},{"time":0.2667,"angle":8.8},{"time":0.4,"angle":-0.1},{"time":0.4667,"angle":-4.55},{"time":0.6667,"angle":8.8},{"time":0.8,"angle":-0.1}]},"017_fish_G3_bian_eye":{"translate":[{"time":0,"x":2.23,"y":2.03},{"time":0.2,"x":-3.62,"y":0.88},{"time":0.4,"x":2.23,"y":2.03},{"time":0.6,"x":-3.62,"y":0.88},{"time":0.8,"x":2.23,"y":2.03}]},"017_fish_G3_water":{"rotate":[{"time":0,"angle":-215.76},{"time":0.2,"angle":0},{"time":0.4,"angle":-215.76},{"time":0.6,"angle":0},{"time":0.8,"angle":-215.76}],"scale":[{"time":0,"x":0.944,"y":1},{"time":0.2,"x":1.378,"y":1},{"time":0.4,"x":0.944,"y":1},{"time":0.6,"x":1.378,"y":1},{"time":0.8,"x":0.944,"y":1}]},"017_fish_G3_bian01":{"rotate":[{"time":0,"angle":15.74},{"time":0.0667,"angle":-327.24},{"time":0.2667,"angle":-18.31},{"time":0.4,"angle":15.74},{"time":0.4667,"angle":-327.24},{"time":0.6667,"angle":-18.31},{"time":0.8,"angle":15.74}],"scale":[{"time":0,"x":0.828,"y":1},{"time":0.0667,"x":0.916,"y":1},{"time":0.2667,"x":0.653,"y":1},{"time":0.4,"x":0.828,"y":1},{"time":0.4667,"x":0.916,"y":1},{"time":0.6667,"x":0.653,"y":1},{"time":0.8,"x":0.828,"y":1}]}},"drawOrder":[{"time":0,"offsets":[{"slot":"017_fish_G3_cap02","offset":3},{"slot":"017_fish_G1_hair01","offset":1},{"slot":"017_fish_G3_cap01","offset":2}]}]}}}