{"skeleton":{"hash":"5Vpzv3n11RppBvk3T3+oGQBmmNY","spine":"3.6.53","width":451.67,"height":306.99},"bones":[{"name":"root","rotation":0.41}],"slots":[{"name":"caideng","bone":"root","attachment":"caideng1"}],"skins":{"default":{"caideng":{"caideng":{"width":451,"height":306},"caideng1":{"rotation":-0.29,"width":451,"height":306}}}},"animations":{"quick":{"slots":{"caideng":{"attachment":[{"time":0,"name":"caideng"},{"time":0.0667,"name":"caideng1"},{"time":0.1333,"name":"caideng"},{"time":0.2,"name":"caideng1"},{"time":0.2667,"name":"caideng"}]}}},"slow":{"slots":{"caideng":{"attachment":[{"time":0,"name":"caideng1"},{"time":0.1,"name":"caideng"},{"time":0.2,"name":"caideng1"},{"time":0.3333,"name":"caideng"},{"time":0.4667,"name":"caideng1"},{"time":0.6333,"name":"caideng"},{"time":0.8,"name":"caideng1"},{"time":1.1333,"name":"caideng"},{"time":1.4667,"name":"caideng1"},{"time":1.8333,"name":"caideng"},{"time":2.2,"name":"caideng1"}]}}}}}